[ {
  "income_more_than" : "0",
  "family_size" : "1",
  "hhc_options_reduced_fee_level" : "1",
  "income_less_than" : "16335"
}
, {
  "income_more_than" : "0",
  "family_size" : "2",
  "hhc_options_reduced_fee_level" : "1",
  "income_less_than" : "22065"
}
, {
  "income_more_than" : "0",
  "family_size" : "3",
  "hhc_options_reduced_fee_level" : "1",
  "income_less_than" : "27795"
}
, {
  "income_more_than" : "0",
  "family_size" : "4",
  "hhc_options_reduced_fee_level" : "1",
  "income_less_than" : "33525"
}
, {
  "income_more_than" : "0",
  "family_size" : "5",
  "hhc_options_reduced_fee_level" : "1",
  "income_less_than" : "39255"
}
, {
  "income_more_than" : "0",
  "family_size" : "6",
  "hhc_options_reduced_fee_level" : "1",
  "income_less_than" : "44985"
}
, {
  "income_more_than" : "0",
  "family_size" : "7",
  "hhc_options_reduced_fee_level" : "1",
  "income_less_than" : "50715"
}
, {
  "income_more_than" : "16336",
  "family_size" : "1",
  "hhc_options_reduced_fee_level" : "2",
  "income_less_than" : "21780"
}
, {
  "income_more_than" : "22066",
  "family_size" : "2",
  "hhc_options_reduced_fee_level" : "2",
  "income_less_than" : "29420"
}
, {
  "income_more_than" : "27796",
  "family_size" : "3",
  "hhc_options_reduced_fee_level" : "2",
  "income_less_than" : "37060"
}
, {
  "income_more_than" : "33526",
  "family_size" : "4",
  "hhc_options_reduced_fee_level" : "2",
  "income_less_than" : "44700"
}
, {
  "income_more_than" : "39256",
  "family_size" : "5",
  "hhc_options_reduced_fee_level" : "2",
  "income_less_than" : "52340"
}
, {
  "income_more_than" : "44986",
  "family_size" : "6",
  "hhc_options_reduced_fee_level" : "2",
  "income_less_than" : "59980"
}
, {
  "income_more_than" : "50716",
  "family_size" : "7",
  "hhc_options_reduced_fee_level" : "2",
  "income_less_than" : "67620"
}
, {
  "income_more_than" : "21781",
  "family_size" : "1",
  "hhc_options_reduced_fee_level" : "3",
  "income_less_than" : "27225"
}
, {
  "income_more_than" : "29421",
  "family_size" : "2",
  "hhc_options_reduced_fee_level" : "3",
  "income_less_than" : "36775"
}
, {
  "income_more_than" : "37061",
  "family_size" : "3",
  "hhc_options_reduced_fee_level" : "3",
  "income_less_than" : "46325"
}
, {
  "income_more_than" : "44701",
  "family_size" : "4",
  "hhc_options_reduced_fee_level" : "3",
  "income_less_than" : "55875"
}
, {
  "income_more_than" : "52341",
  "family_size" : "5",
  "hhc_options_reduced_fee_level" : "3",
  "income_less_than" : "65425"
}
, {
  "income_more_than" : "59981",
  "family_size" : "6",
  "hhc_options_reduced_fee_level" : "3",
  "income_less_than" : "74975"
}
, {
  "income_more_than" : "67621",
  "family_size" : "7",
  "hhc_options_reduced_fee_level" : "3",
  "income_less_than" : "84525"
}
, {
  "income_more_than" : "27226",
  "family_size" : "1",
  "hhc_options_reduced_fee_level" : "4",
  "income_less_than" : "32670"
}
, {
  "income_more_than" : "36776",
  "family_size" : "2",
  "hhc_options_reduced_fee_level" : "4",
  "income_less_than" : "44130"
}
, {
  "income_more_than" : "46326",
  "family_size" : "3",
  "hhc_options_reduced_fee_level" : "4",
  "income_less_than" : "55590"
}
, {
  "income_more_than" : "55876",
  "family_size" : "4",
  "hhc_options_reduced_fee_level" : "4",
  "income_less_than" : "67050"
}
, {
  "income_more_than" : "65426",
  "family_size" : "5",
  "hhc_options_reduced_fee_level" : "4",
  "income_less_than" : "78510"
}
, {
  "income_more_than" : "74976",
  "family_size" : "6",
  "hhc_options_reduced_fee_level" : "4",
  "income_less_than" : "89970"
}
, {
  "income_more_than" : "84526",
  "family_size" : "7",
  "hhc_options_reduced_fee_level" : "4",
  "income_less_than" : "101430"
}
, {
  "income_more_than" : "32671",
  "family_size" : "1",
  "hhc_options_reduced_fee_level" : "5",
  "income_less_than" : "38115"
}
, {
  "income_more_than" : "44131",
  "family_size" : "2",
  "hhc_options_reduced_fee_level" : "5",
  "income_less_than" : "51485"
}
, {
  "income_more_than" : "55591",
  "family_size" : "3",
  "hhc_options_reduced_fee_level" : "5",
  "income_less_than" : "64855"
}
, {
  "income_more_than" : "67051",
  "family_size" : "4",
  "hhc_options_reduced_fee_level" : "5",
  "income_less_than" : "78225"
}
, {
  "income_more_than" : "78511",
  "family_size" : "5",
  "hhc_options_reduced_fee_level" : "5",
  "income_less_than" : "91595"
}
, {
  "income_more_than" : "89971",
  "family_size" : "6",
  "hhc_options_reduced_fee_level" : "5",
  "income_less_than" : "104965"
}
, {
  "income_more_than" : "101431",
  "family_size" : "7",
  "hhc_options_reduced_fee_level" : "5",
  "income_less_than" : "118335"
}
, {
  "income_more_than" : "38116",
  "family_size" : "1",
  "hhc_options_reduced_fee_level" : "6",
  "income_less_than" : "43560"
}
, {
  "income_more_than" : "51486",
  "family_size" : "2",
  "hhc_options_reduced_fee_level" : "6",
  "income_less_than" : "58840"
}
, {
  "income_more_than" : "64856",
  "family_size" : "3",
  "hhc_options_reduced_fee_level" : "6",
  "income_less_than" : "74120"
}
, {
  "income_more_than" : "78226",
  "family_size" : "4",
  "hhc_options_reduced_fee_level" : "6",
  "income_less_than" : "89400"
}
, {
  "income_more_than" : "91596",
  "family_size" : "5",
  "hhc_options_reduced_fee_level" : "6",
  "income_less_than" : "104680"
}
, {
  "income_more_than" : "104966",
  "family_size" : "6",
  "hhc_options_reduced_fee_level" : "6",
  "income_less_than" : "119960"
}
, {
  "income_more_than" : "118336",
  "family_size" : "7",
  "hhc_options_reduced_fee_level" : "6",
  "income_less_than" : "135240"
}
, {
  "income_more_than" : "43561",
  "family_size" : "1",
  "hhc_options_reduced_fee_level" : "7"
}
, {
  "income_more_than" : "58841",
  "family_size" : "2",
  "hhc_options_reduced_fee_level" : "7"
}
, {
  "income_more_than" : "74121",
  "family_size" : "3",
  "hhc_options_reduced_fee_level" : "7"
}
, {
  "income_more_than" : "89401",
  "family_size" : "4",
  "hhc_options_reduced_fee_level" : "7"
}
, {
  "income_more_than" : "104681",
  "family_size" : "5",
  "hhc_options_reduced_fee_level" : "7"
}
, {
  "income_more_than" : "119961",
  "family_size" : "6",
  "hhc_options_reduced_fee_level" : "7"
}
, {
  "income_more_than" : "135241",
  "family_size" : "7",
  "hhc_options_reduced_fee_level" : "7"
}
 ]