[ {
  "year_2017" : "14368",
  "year_2018" : "15249",
  "year_2015" : "14205",
  "year_2016" : "14082",
  "year_2013" : "14275",
  "year_2014" : "13787",
  "year_2011" : "14021",
  "year_2012" : "14442",
  "borough" : "BRONX",
  "year_2008" : "14350",
  "year_2009" : "14290",
  "grade" : "10",
  "year_2010" : "14022"
}
, {
  "year_2017" : "10151",
  "year_2018" : "10372",
  "year_2015" : "9906",
  "year_2016" : "10217",
  "year_2013" : "10367",
  "year_2014" : "10247",
  "year_2011" : "10034",
  "year_2012" : "10027",
  "borough" : "BRONX",
  "year_2008" : "11162",
  "year_2009" : "10252",
  "grade" : "11",
  "year_2010" : "10216"
}
, {
  "year_2017" : "9253",
  "year_2018" : "9203",
  "year_2015" : "9271",
  "year_2016" : "8967",
  "year_2013" : "9058",
  "year_2014" : "9379",
  "year_2011" : "9224",
  "year_2012" : "9065",
  "borough" : "BRONX",
  "year_2008" : "9993",
  "year_2009" : "10072",
  "grade" : "12",
  "year_2010" : "9254"
}
, {
  "year_2017" : "16487",
  "year_2018" : "16880",
  "year_2015" : "15252",
  "year_2016" : "15555",
  "year_2013" : "14952",
  "year_2014" : "15398",
  "year_2011" : "15668",
  "year_2012" : "15485",
  "borough" : "BRONX",
  "year_2008" : "15529",
  "year_2009" : "15230",
  "grade" : "9",
  "year_2010" : "15229"
}
, {
  "year_2017" : "1846",
  "year_2018" : "1846",
  "year_2015" : "1846",
  "year_2016" : "1846",
  "year_2013" : "1846",
  "year_2014" : "1846",
  "year_2011" : "1846",
  "year_2012" : "1846",
  "borough" : "BRONX",
  "year_2008" : "1846",
  "year_2009" : "1846",
  "grade" : "GED (16-20)",
  "year_2010" : "1846"
}
, {
  "year_2017" : "31",
  "year_2018" : "31",
  "year_2015" : "31",
  "year_2016" : "31",
  "year_2013" : "31",
  "year_2014" : "31",
  "year_2011" : "31",
  "year_2012" : "31",
  "borough" : "BRONX",
  "year_2008" : "31",
  "year_2009" : "31",
  "grade" : "GED (21+)",
  "year_2010" : "31"
}
, {
  "year_2017" : "9282",
  "year_2018" : "9488",
  "year_2015" : "8994",
  "year_2016" : "9194",
  "year_2013" : "8469",
  "year_2014" : "8790",
  "year_2011" : "7850",
  "year_2012" : "8331",
  "borough" : "BRONX",
  "year_2008" : "7235",
  "year_2009" : "7593",
  "grade" : "Spec Ed",
  "year_2010" : "7768"
}
, {
  "year_2017" : "20996",
  "year_2018" : "21937",
  "year_2015" : "20758",
  "year_2016" : "20955",
  "year_2013" : "20464",
  "year_2014" : "20416",
  "year_2011" : "20475",
  "year_2012" : "20966",
  "borough" : "BROOKLYN",
  "year_2008" : "22489",
  "year_2009" : "21121",
  "grade" : "10",
  "year_2010" : "20727"
}
, {
  "year_2017" : "14759",
  "year_2018" : "14782",
  "year_2015" : "14323",
  "year_2016" : "14589",
  "year_2013" : "14692",
  "year_2014" : "14350",
  "year_2011" : "14492",
  "year_2012" : "14325",
  "borough" : "BROOKLYN",
  "year_2008" : "16876",
  "year_2009" : "15709",
  "grade" : "11",
  "year_2010" : "14765"
}
, {
  "year_2017" : "14523",
  "year_2018" : "14715",
  "year_2015" : "14262",
  "year_2016" : "14243",
  "year_2013" : "14212",
  "year_2014" : "14593",
  "year_2011" : "14630",
  "year_2012" : "14366",
  "borough" : "BROOKLYN",
  "year_2008" : "16589",
  "year_2009" : "16690",
  "grade" : "12",
  "year_2010" : "15558"
}
, {
  "year_2017" : "21853",
  "year_2018" : "22682",
  "year_2015" : "20914",
  "year_2016" : "20950",
  "year_2013" : "20514",
  "year_2014" : "20797",
  "year_2011" : "21122",
  "year_2012" : "20587",
  "borough" : "BROOKLYN",
  "year_2008" : "21390",
  "year_2009" : "20973",
  "grade" : "9",
  "year_2010" : "20685"
}
, {
  "year_2017" : "2048",
  "year_2018" : "2048",
  "year_2015" : "2048",
  "year_2016" : "2048",
  "year_2013" : "2048",
  "year_2014" : "2048",
  "year_2011" : "2048",
  "year_2012" : "2048",
  "borough" : "BROOKLYN",
  "year_2008" : "2048",
  "year_2009" : "2048",
  "grade" : "GED (16-20)",
  "year_2010" : "2048"
}
, {
  "year_2017" : "10",
  "year_2018" : "10",
  "year_2015" : "10",
  "year_2016" : "10",
  "year_2013" : "10",
  "year_2014" : "10",
  "year_2011" : "10",
  "year_2012" : "10",
  "borough" : "BROOKLYN",
  "year_2008" : "10",
  "year_2009" : "10",
  "grade" : "GED (21+)",
  "year_2010" : "10"
}
, {
  "year_2017" : "12791",
  "year_2018" : "13313",
  "year_2015" : "11280",
  "year_2016" : "12045",
  "year_2013" : "10420",
  "year_2014" : "10831",
  "year_2011" : "9609",
  "year_2012" : "10180",
  "borough" : "BROOKLYN",
  "year_2008" : "8538",
  "year_2009" : "8976",
  "grade" : "Spec Ed",
  "year_2010" : "9354"
}
, {
  "year_2017" : "14873",
  "year_2018" : "15358",
  "year_2015" : "14418",
  "year_2016" : "14880",
  "year_2013" : "14294",
  "year_2014" : "13965",
  "year_2011" : "14439",
  "year_2012" : "14740",
  "borough" : "MANHATTAN",
  "year_2008" : "16143",
  "year_2009" : "15257",
  "grade" : "10",
  "year_2010" : "14768"
}
, {
  "year_2017" : "12228",
  "year_2018" : "12250",
  "year_2015" : "11345",
  "year_2016" : "11768",
  "year_2013" : "11864",
  "year_2014" : "11550",
  "year_2011" : "11813",
  "year_2012" : "11581",
  "borough" : "MANHATTAN",
  "year_2008" : "13435",
  "year_2009" : "12802",
  "grade" : "11",
  "year_2010" : "12147"
}
, {
  "year_2017" : "10683",
  "year_2018" : "11118",
  "year_2015" : "10453",
  "year_2016" : "10284",
  "year_2013" : "10461",
  "year_2014" : "10729",
  "year_2011" : "10950",
  "year_2012" : "10662",
  "borough" : "MANHATTAN",
  "year_2008" : "11932",
  "year_2009" : "12080",
  "grade" : "12",
  "year_2010" : "11526"
}
, {
  "year_2017" : "15777",
  "year_2018" : "16048",
  "year_2015" : "15364",
  "year_2016" : "15321",
  "year_2013" : "14500",
  "year_2014" : "14907",
  "year_2011" : "15367",
  "year_2012" : "14894",
  "borough" : "MANHATTAN",
  "year_2008" : "16018",
  "year_2009" : "15478",
  "grade" : "9",
  "year_2010" : "15105"
}
, {
  "year_2017" : "1453",
  "year_2018" : "1453",
  "year_2015" : "1453",
  "year_2016" : "1453",
  "year_2013" : "1453",
  "year_2014" : "1453",
  "year_2011" : "1453",
  "year_2012" : "1453",
  "borough" : "MANHATTAN",
  "year_2008" : "1453",
  "year_2009" : "1453",
  "grade" : "GED (16-20)",
  "year_2010" : "1453"
}
, {
  "year_2017" : "14",
  "year_2018" : "14",
  "year_2015" : "14",
  "year_2016" : "14",
  "year_2013" : "14",
  "year_2014" : "14",
  "year_2011" : "14",
  "year_2012" : "14",
  "borough" : "MANHATTAN",
  "year_2008" : "14",
  "year_2009" : "14",
  "grade" : "GED (21+)",
  "year_2010" : "14"
}
, {
  "year_2017" : "7484",
  "year_2018" : "7590",
  "year_2015" : "6831",
  "year_2016" : "7314",
  "year_2013" : "5983",
  "year_2014" : "6333",
  "year_2011" : "5420",
  "year_2012" : "5692",
  "borough" : "MANHATTAN",
  "year_2008" : "4829",
  "year_2009" : "5058",
  "grade" : "Spec Ed",
  "year_2010" : "5214"
}
, {
  "year_2017" : "75161",
  "year_2018" : "78363",
  "year_2015" : "74178",
  "year_2016" : "74966",
  "year_2013" : "72900",
  "year_2014" : "72441",
  "year_2011" : "72008",
  "year_2012" : "74348",
  "borough" : "NYC",
  "year_2008" : "76620",
  "year_2009" : "73745",
  "grade" : "10",
  "year_2010" : "72892"
}
, {
  "year_2017" : "57691",
  "year_2018" : "57786",
  "year_2015" : "55448",
  "year_2016" : "56896",
  "year_2013" : "56767",
  "year_2014" : "55645",
  "year_2011" : "55409",
  "year_2012" : "54798",
  "borough" : "NYC",
  "year_2008" : "62105",
  "year_2009" : "58046",
  "grade" : "11",
  "year_2010" : "55957"
}
, {
  "year_2017" : "53934",
  "year_2018" : "54771",
  "year_2015" : "52637",
  "year_2016" : "52522",
  "year_2013" : "51759",
  "year_2014" : "53703",
  "year_2011" : "52750",
  "year_2012" : "52287",
  "borough" : "NYC",
  "year_2008" : "57351",
  "year_2009" : "58516",
  "grade" : "12",
  "year_2010" : "54726"
}
, {
  "year_2017" : "82122",
  "year_2018" : "84539",
  "year_2015" : "78653",
  "year_2016" : "78860",
  "year_2013" : "76337",
  "year_2014" : "78005",
  "year_2011" : "78437",
  "year_2012" : "76946",
  "borough" : "NYC",
  "year_2008" : "78117",
  "year_2009" : "77181",
  "grade" : "9",
  "year_2010" : "76146"
}
, {
  "year_2017" : "6314",
  "year_2018" : "6314",
  "year_2015" : "6314",
  "year_2016" : "6314",
  "year_2013" : "6314",
  "year_2014" : "6314",
  "year_2011" : "6314",
  "year_2012" : "6314",
  "borough" : "NYC",
  "year_2008" : "6314",
  "year_2009" : "6314",
  "grade" : "GED (16-20)",
  "year_2010" : "6314"
}
, {
  "year_2017" : "55",
  "year_2018" : "55",
  "year_2015" : "55",
  "year_2016" : "55",
  "year_2013" : "55",
  "year_2014" : "55",
  "year_2011" : "55",
  "year_2012" : "55",
  "borough" : "NYC",
  "year_2008" : "55",
  "year_2009" : "55",
  "grade" : "GED (21+)",
  "year_2010" : "55"
}
, {
  "year_2017" : "44490",
  "year_2018" : "46020",
  "year_2015" : "39977",
  "year_2016" : "42445",
  "year_2013" : "35748",
  "year_2014" : "37781",
  "year_2011" : "32274",
  "year_2012" : "34194",
  "borough" : "NYC",
  "year_2008" : "28449",
  "year_2009" : "30073",
  "grade" : "Spec Ed",
  "year_2010" : "31295"
}
, {
  "year_2017" : "20905",
  "year_2018" : "21505",
  "year_2015" : "20501",
  "year_2016" : "20932",
  "year_2013" : "19805",
  "year_2014" : "20070",
  "year_2011" : "18987",
  "year_2012" : "19992",
  "borough" : "QUEENS",
  "year_2008" : "19346",
  "year_2009" : "18723",
  "grade" : "10",
  "year_2010" : "19139"
}
, {
  "year_2017" : "17112",
  "year_2018" : "17044",
  "year_2015" : "16343",
  "year_2016" : "16718",
  "year_2013" : "16318",
  "year_2014" : "16104",
  "year_2011" : "15533",
  "year_2012" : "15439",
  "borough" : "QUEENS",
  "year_2008" : "17003",
  "year_2009" : "15681",
  "grade" : "11",
  "year_2010" : "15197"
}
, {
  "year_2017" : "16305",
  "year_2018" : "16710",
  "year_2015" : "15671",
  "year_2016" : "15921",
  "year_2013" : "15017",
  "year_2014" : "15903",
  "year_2011" : "14763",
  "year_2012" : "15091",
  "borough" : "QUEENS",
  "year_2008" : "15519",
  "year_2009" : "16488",
  "grade" : "12",
  "year_2010" : "15225"
}
, {
  "year_2017" : "23259",
  "year_2018" : "24202",
  "year_2015" : "22617",
  "year_2016" : "22622",
  "year_2013" : "21779",
  "year_2014" : "22204",
  "year_2011" : "21678",
  "year_2012" : "21532",
  "borough" : "QUEENS",
  "year_2008" : "20407",
  "year_2009" : "20859",
  "grade" : "9",
  "year_2010" : "20656"
}
, {
  "year_2017" : "836",
  "year_2018" : "836",
  "year_2015" : "836",
  "year_2016" : "836",
  "year_2013" : "836",
  "year_2014" : "836",
  "year_2011" : "836",
  "year_2012" : "836",
  "borough" : "QUEENS",
  "year_2008" : "836",
  "year_2009" : "836",
  "grade" : "GED (16-20)",
  "year_2010" : "836"
}
, {
  "year_2017" : "0",
  "year_2018" : "0",
  "year_2015" : "0",
  "year_2016" : "0",
  "year_2013" : "0",
  "year_2014" : "0",
  "year_2011" : "0",
  "year_2012" : "0",
  "borough" : "QUEENS",
  "year_2008" : "0",
  "year_2009" : "0",
  "grade" : "GED (21+)",
  "year_2010" : "0"
}
, {
  "year_2017" : "11261",
  "year_2018" : "11775",
  "year_2015" : "9832",
  "year_2016" : "10522",
  "year_2013" : "8232",
  "year_2014" : "8946",
  "year_2011" : "7111",
  "year_2012" : "7588",
  "borough" : "QUEENS",
  "year_2008" : "5981",
  "year_2009" : "6418",
  "grade" : "Spec Ed",
  "year_2010" : "6789"
}
, {
  "year_2017" : "4018",
  "year_2018" : "4314",
  "year_2015" : "4297",
  "year_2016" : "4116",
  "year_2013" : "4061",
  "year_2014" : "4203",
  "year_2011" : "4086",
  "year_2012" : "4207",
  "borough" : "RICHMOND",
  "year_2008" : "4292",
  "year_2009" : "4354",
  "grade" : "10",
  "year_2010" : "4236"
}
, {
  "year_2017" : "3441",
  "year_2018" : "3337",
  "year_2015" : "3530",
  "year_2016" : "3605",
  "year_2013" : "3526",
  "year_2014" : "3394",
  "year_2011" : "3537",
  "year_2012" : "3426",
  "borough" : "RICHMOND",
  "year_2008" : "3629",
  "year_2009" : "3601",
  "grade" : "11",
  "year_2010" : "3632"
}
, {
  "year_2017" : "3171",
  "year_2018" : "3025",
  "year_2015" : "2981",
  "year_2016" : "3106",
  "year_2013" : "3011",
  "year_2014" : "3099",
  "year_2011" : "3183",
  "year_2012" : "3103",
  "borough" : "RICHMOND",
  "year_2008" : "3318",
  "year_2009" : "3186",
  "grade" : "12",
  "year_2010" : "3163"
}
, {
  "year_2017" : "4747",
  "year_2018" : "4727",
  "year_2015" : "4507",
  "year_2016" : "4412",
  "year_2013" : "4592",
  "year_2014" : "4699",
  "year_2011" : "4602",
  "year_2012" : "4448",
  "borough" : "RICHMOND",
  "year_2008" : "4773",
  "year_2009" : "4641",
  "grade" : "9",
  "year_2010" : "4470"
}
, {
  "year_2017" : "131",
  "year_2018" : "131",
  "year_2015" : "131",
  "year_2016" : "131",
  "year_2013" : "131",
  "year_2014" : "131",
  "year_2011" : "131",
  "year_2012" : "131",
  "borough" : "RICHMOND",
  "year_2008" : "131",
  "year_2009" : "131",
  "grade" : "GED (16-20)",
  "year_2010" : "131"
}
, {
  "year_2017" : "0",
  "year_2018" : "0",
  "year_2015" : "0",
  "year_2016" : "0",
  "year_2013" : "0",
  "year_2014" : "0",
  "year_2011" : "0",
  "year_2012" : "0",
  "borough" : "RICHMOND",
  "year_2008" : "0",
  "year_2009" : "0",
  "grade" : "GED (21+)",
  "year_2010" : "0"
}
, {
  "year_2017" : "3672",
  "year_2018" : "3854",
  "year_2015" : "3039",
  "year_2016" : "3371",
  "year_2013" : "2644",
  "year_2014" : "2882",
  "year_2011" : "2285",
  "year_2012" : "2402",
  "borough" : "RICHMOND",
  "year_2008" : "1866",
  "year_2009" : "2027",
  "grade" : "Spec Ed",
  "year_2010" : "2170"
}
 ]