[ {
  "fiscal_year_ending_in_june_" : "2006",
  "filed_violation_count" : "113",
  "violation_type" : "Absconder",
  "borough" : "Bronx"
}
, {
  "fiscal_year_ending_in_june_" : "2007",
  "filed_violation_count" : "207",
  "violation_type" : "Absconder",
  "borough" : "Bronx"
}
, {
  "fiscal_year_ending_in_june_" : "2008",
  "filed_violation_count" : "140",
  "violation_type" : "Absconder",
  "borough" : "Bronx"
}
, {
  "fiscal_year_ending_in_june_" : "2009",
  "filed_violation_count" : "147",
  "violation_type" : "Absconder",
  "borough" : "Bronx"
}
, {
  "fiscal_year_ending_in_june_" : "2010",
  "filed_violation_count" : "169",
  "violation_type" : "Absconder",
  "borough" : "Bronx"
}
, {
  "fiscal_year_ending_in_june_" : "2011",
  "filed_violation_count" : "112",
  "violation_type" : "Absconder",
  "borough" : "Bronx"
}
, {
  "fiscal_year_ending_in_june_" : "2012",
  "filed_violation_count" : "118",
  "violation_type" : "Absconder",
  "borough" : "Bronx"
}
, {
  "fiscal_year_ending_in_june_" : "2013",
  "filed_violation_count" : "141",
  "violation_type" : "Absconder",
  "borough" : "Bronx"
}
, {
  "fiscal_year_ending_in_june_" : "2014",
  "filed_violation_count" : "111",
  "violation_type" : "Absconder",
  "borough" : "Bronx"
}
, {
  "fiscal_year_ending_in_june_" : "2015",
  "filed_violation_count" : "135",
  "violation_type" : "Absconder",
  "borough" : "Bronx"
}
, {
  "fiscal_year_ending_in_june_" : "2016",
  "filed_violation_count" : "116",
  "violation_type" : "Absconder",
  "borough" : "Bronx"
}
, {
  "fiscal_year_ending_in_june_" : "2006",
  "filed_violation_count" : "862",
  "violation_type" : "Rearrests",
  "borough" : "Bronx"
}
, {
  "fiscal_year_ending_in_june_" : "2007",
  "filed_violation_count" : "949",
  "violation_type" : "Rearrests",
  "borough" : "Bronx"
}
, {
  "fiscal_year_ending_in_june_" : "2008",
  "filed_violation_count" : "957",
  "violation_type" : "Rearrests",
  "borough" : "Bronx"
}
, {
  "fiscal_year_ending_in_june_" : "2009",
  "filed_violation_count" : "914",
  "violation_type" : "Rearrests",
  "borough" : "Bronx"
}
, {
  "fiscal_year_ending_in_june_" : "2010",
  "filed_violation_count" : "904",
  "violation_type" : "Rearrests",
  "borough" : "Bronx"
}
, {
  "fiscal_year_ending_in_june_" : "2011",
  "filed_violation_count" : "493",
  "violation_type" : "Rearrests",
  "borough" : "Bronx"
}
, {
  "fiscal_year_ending_in_june_" : "2012",
  "filed_violation_count" : "480",
  "violation_type" : "Rearrests",
  "borough" : "Bronx"
}
, {
  "fiscal_year_ending_in_june_" : "2013",
  "filed_violation_count" : "340",
  "violation_type" : "Rearrests",
  "borough" : "Bronx"
}
, {
  "fiscal_year_ending_in_june_" : "2014",
  "filed_violation_count" : "399",
  "violation_type" : "Rearrests",
  "borough" : "Bronx"
}
, {
  "fiscal_year_ending_in_june_" : "2015",
  "filed_violation_count" : "404",
  "violation_type" : "Rearrests",
  "borough" : "Bronx"
}
, {
  "fiscal_year_ending_in_june_" : "2016",
  "filed_violation_count" : "443",
  "violation_type" : "Rearrests",
  "borough" : "Bronx"
}
, {
  "fiscal_year_ending_in_june_" : "2006",
  "filed_violation_count" : "401",
  "violation_type" : "Technical",
  "borough" : "Bronx"
}
, {
  "fiscal_year_ending_in_june_" : "2007",
  "filed_violation_count" : "322",
  "violation_type" : "Technical",
  "borough" : "Bronx"
}
, {
  "fiscal_year_ending_in_june_" : "2008",
  "filed_violation_count" : "293",
  "violation_type" : "Technical",
  "borough" : "Bronx"
}
, {
  "fiscal_year_ending_in_june_" : "2009",
  "filed_violation_count" : "350",
  "violation_type" : "Technical",
  "borough" : "Bronx"
}
, {
  "fiscal_year_ending_in_june_" : "2010",
  "filed_violation_count" : "282",
  "violation_type" : "Technical",
  "borough" : "Bronx"
}
, {
  "fiscal_year_ending_in_june_" : "2011",
  "filed_violation_count" : "107",
  "violation_type" : "Technical",
  "borough" : "Bronx"
}
, {
  "fiscal_year_ending_in_june_" : "2012",
  "filed_violation_count" : "88",
  "violation_type" : "Technical",
  "borough" : "Bronx"
}
, {
  "fiscal_year_ending_in_june_" : "2013",
  "filed_violation_count" : "120",
  "violation_type" : "Technical",
  "borough" : "Bronx"
}
, {
  "fiscal_year_ending_in_june_" : "2014",
  "filed_violation_count" : "44",
  "violation_type" : "Technical",
  "borough" : "Bronx"
}
, {
  "fiscal_year_ending_in_june_" : "2015",
  "filed_violation_count" : "39",
  "violation_type" : "Technical",
  "borough" : "Bronx"
}
, {
  "fiscal_year_ending_in_june_" : "2016",
  "filed_violation_count" : "43",
  "violation_type" : "Technical",
  "borough" : "Bronx"
}
, {
  "fiscal_year_ending_in_june_" : "2006",
  "filed_violation_count" : "10",
  "violation_type" : "Absconder",
  "borough" : "Brooklyn"
}
, {
  "fiscal_year_ending_in_june_" : "2007",
  "filed_violation_count" : "5",
  "violation_type" : "Absconder",
  "borough" : "Brooklyn"
}
, {
  "fiscal_year_ending_in_june_" : "2008",
  "filed_violation_count" : "14",
  "violation_type" : "Absconder",
  "borough" : "Brooklyn"
}
, {
  "fiscal_year_ending_in_june_" : "2009",
  "filed_violation_count" : "8",
  "violation_type" : "Absconder",
  "borough" : "Brooklyn"
}
, {
  "fiscal_year_ending_in_june_" : "2010",
  "filed_violation_count" : "45",
  "violation_type" : "Absconder",
  "borough" : "Brooklyn"
}
, {
  "fiscal_year_ending_in_june_" : "2011",
  "filed_violation_count" : "96",
  "violation_type" : "Absconder",
  "borough" : "Brooklyn"
}
, {
  "fiscal_year_ending_in_june_" : "2012",
  "filed_violation_count" : "137",
  "violation_type" : "Absconder",
  "borough" : "Brooklyn"
}
, {
  "fiscal_year_ending_in_june_" : "2013",
  "filed_violation_count" : "101",
  "violation_type" : "Absconder",
  "borough" : "Brooklyn"
}
, {
  "fiscal_year_ending_in_june_" : "2014",
  "filed_violation_count" : "109",
  "violation_type" : "Absconder",
  "borough" : "Brooklyn"
}
, {
  "fiscal_year_ending_in_june_" : "2015",
  "filed_violation_count" : "104",
  "violation_type" : "Absconder",
  "borough" : "Brooklyn"
}
, {
  "fiscal_year_ending_in_june_" : "2016",
  "filed_violation_count" : "87",
  "violation_type" : "Absconder",
  "borough" : "Brooklyn"
}
, {
  "fiscal_year_ending_in_june_" : "2006",
  "filed_violation_count" : "878",
  "violation_type" : "Rearrests",
  "borough" : "Brooklyn"
}
, {
  "fiscal_year_ending_in_june_" : "2007",
  "filed_violation_count" : "835",
  "violation_type" : "Rearrests",
  "borough" : "Brooklyn"
}
, {
  "fiscal_year_ending_in_june_" : "2008",
  "filed_violation_count" : "882",
  "violation_type" : "Rearrests",
  "borough" : "Brooklyn"
}
, {
  "fiscal_year_ending_in_june_" : "2009",
  "filed_violation_count" : "801",
  "violation_type" : "Rearrests",
  "borough" : "Brooklyn"
}
, {
  "fiscal_year_ending_in_june_" : "2010",
  "filed_violation_count" : "839",
  "violation_type" : "Rearrests",
  "borough" : "Brooklyn"
}
, {
  "fiscal_year_ending_in_june_" : "2011",
  "filed_violation_count" : "494",
  "violation_type" : "Rearrests",
  "borough" : "Brooklyn"
}
, {
  "fiscal_year_ending_in_june_" : "2012",
  "filed_violation_count" : "380",
  "violation_type" : "Rearrests",
  "borough" : "Brooklyn"
}
, {
  "fiscal_year_ending_in_june_" : "2013",
  "filed_violation_count" : "381",
  "violation_type" : "Rearrests",
  "borough" : "Brooklyn"
}
, {
  "fiscal_year_ending_in_june_" : "2014",
  "filed_violation_count" : "321",
  "violation_type" : "Rearrests",
  "borough" : "Brooklyn"
}
, {
  "fiscal_year_ending_in_june_" : "2015",
  "filed_violation_count" : "265",
  "violation_type" : "Rearrests",
  "borough" : "Brooklyn"
}
, {
  "fiscal_year_ending_in_june_" : "2016",
  "filed_violation_count" : "292",
  "violation_type" : "Rearrests",
  "borough" : "Brooklyn"
}
, {
  "fiscal_year_ending_in_june_" : "2006",
  "filed_violation_count" : "628",
  "violation_type" : "Technical",
  "borough" : "Brooklyn"
}
, {
  "fiscal_year_ending_in_june_" : "2007",
  "filed_violation_count" : "492",
  "violation_type" : "Technical",
  "borough" : "Brooklyn"
}
, {
  "fiscal_year_ending_in_june_" : "2008",
  "filed_violation_count" : "594",
  "violation_type" : "Technical",
  "borough" : "Brooklyn"
}
, {
  "fiscal_year_ending_in_june_" : "2009",
  "filed_violation_count" : "528",
  "violation_type" : "Technical",
  "borough" : "Brooklyn"
}
, {
  "fiscal_year_ending_in_june_" : "2010",
  "filed_violation_count" : "449",
  "violation_type" : "Technical",
  "borough" : "Brooklyn"
}
, {
  "fiscal_year_ending_in_june_" : "2011",
  "filed_violation_count" : "160",
  "violation_type" : "Technical",
  "borough" : "Brooklyn"
}
, {
  "fiscal_year_ending_in_june_" : "2012",
  "filed_violation_count" : "68",
  "violation_type" : "Technical",
  "borough" : "Brooklyn"
}
, {
  "fiscal_year_ending_in_june_" : "2013",
  "filed_violation_count" : "55",
  "violation_type" : "Technical",
  "borough" : "Brooklyn"
}
, {
  "fiscal_year_ending_in_june_" : "2014",
  "filed_violation_count" : "55",
  "violation_type" : "Technical",
  "borough" : "Brooklyn"
}
, {
  "fiscal_year_ending_in_june_" : "2015",
  "filed_violation_count" : "47",
  "violation_type" : "Technical",
  "borough" : "Brooklyn"
}
, {
  "fiscal_year_ending_in_june_" : "2016",
  "filed_violation_count" : "66",
  "violation_type" : "Technical",
  "borough" : "Brooklyn"
}
, {
  "fiscal_year_ending_in_june_" : "2006",
  "filed_violation_count" : "221",
  "violation_type" : "Absconder",
  "borough" : "Manhattan"
}
, {
  "fiscal_year_ending_in_june_" : "2007",
  "filed_violation_count" : "255",
  "violation_type" : "Absconder",
  "borough" : "Manhattan"
}
, {
  "fiscal_year_ending_in_june_" : "2008",
  "filed_violation_count" : "307",
  "violation_type" : "Absconder",
  "borough" : "Manhattan"
}
, {
  "fiscal_year_ending_in_june_" : "2009",
  "filed_violation_count" : "184",
  "violation_type" : "Absconder",
  "borough" : "Manhattan"
}
, {
  "fiscal_year_ending_in_june_" : "2010",
  "filed_violation_count" : "187",
  "violation_type" : "Absconder",
  "borough" : "Manhattan"
}
, {
  "fiscal_year_ending_in_june_" : "2011",
  "filed_violation_count" : "112",
  "violation_type" : "Absconder",
  "borough" : "Manhattan"
}
, {
  "fiscal_year_ending_in_june_" : "2012",
  "filed_violation_count" : "89",
  "violation_type" : "Absconder",
  "borough" : "Manhattan"
}
, {
  "fiscal_year_ending_in_june_" : "2013",
  "filed_violation_count" : "105",
  "violation_type" : "Absconder",
  "borough" : "Manhattan"
}
, {
  "fiscal_year_ending_in_june_" : "2014",
  "filed_violation_count" : "102",
  "violation_type" : "Absconder",
  "borough" : "Manhattan"
}
, {
  "fiscal_year_ending_in_june_" : "2015",
  "filed_violation_count" : "110",
  "violation_type" : "Absconder",
  "borough" : "Manhattan"
}
, {
  "fiscal_year_ending_in_june_" : "2016",
  "filed_violation_count" : "116",
  "violation_type" : "Absconder",
  "borough" : "Manhattan"
}
, {
  "fiscal_year_ending_in_june_" : "2006",
  "filed_violation_count" : "923",
  "violation_type" : "Rearrests",
  "borough" : "Manhattan"
}
, {
  "fiscal_year_ending_in_june_" : "2007",
  "filed_violation_count" : "719",
  "violation_type" : "Rearrests",
  "borough" : "Manhattan"
}
, {
  "fiscal_year_ending_in_june_" : "2008",
  "filed_violation_count" : "869",
  "violation_type" : "Rearrests",
  "borough" : "Manhattan"
}
, {
  "fiscal_year_ending_in_june_" : "2009",
  "filed_violation_count" : "714",
  "violation_type" : "Rearrests",
  "borough" : "Manhattan"
}
, {
  "fiscal_year_ending_in_june_" : "2010",
  "filed_violation_count" : "708",
  "violation_type" : "Rearrests",
  "borough" : "Manhattan"
}
, {
  "fiscal_year_ending_in_june_" : "2011",
  "filed_violation_count" : "465",
  "violation_type" : "Rearrests",
  "borough" : "Manhattan"
}
, {
  "fiscal_year_ending_in_june_" : "2012",
  "filed_violation_count" : "461",
  "violation_type" : "Rearrests",
  "borough" : "Manhattan"
}
, {
  "fiscal_year_ending_in_june_" : "2013",
  "filed_violation_count" : "396",
  "violation_type" : "Rearrests",
  "borough" : "Manhattan"
}
, {
  "fiscal_year_ending_in_june_" : "2014",
  "filed_violation_count" : "476",
  "violation_type" : "Rearrests",
  "borough" : "Manhattan"
}
, {
  "fiscal_year_ending_in_june_" : "2015",
  "filed_violation_count" : "424",
  "violation_type" : "Rearrests",
  "borough" : "Manhattan"
}
, {
  "fiscal_year_ending_in_june_" : "2016",
  "filed_violation_count" : "450",
  "violation_type" : "Rearrests",
  "borough" : "Manhattan"
}
, {
  "fiscal_year_ending_in_june_" : "2006",
  "filed_violation_count" : "605",
  "violation_type" : "Technical",
  "borough" : "Manhattan"
}
, {
  "fiscal_year_ending_in_june_" : "2007",
  "filed_violation_count" : "402",
  "violation_type" : "Technical",
  "borough" : "Manhattan"
}
, {
  "fiscal_year_ending_in_june_" : "2008",
  "filed_violation_count" : "388",
  "violation_type" : "Technical",
  "borough" : "Manhattan"
}
, {
  "fiscal_year_ending_in_june_" : "2009",
  "filed_violation_count" : "334",
  "violation_type" : "Technical",
  "borough" : "Manhattan"
}
, {
  "fiscal_year_ending_in_june_" : "2010",
  "filed_violation_count" : "326",
  "violation_type" : "Technical",
  "borough" : "Manhattan"
}
, {
  "fiscal_year_ending_in_june_" : "2011",
  "filed_violation_count" : "178",
  "violation_type" : "Technical",
  "borough" : "Manhattan"
}
, {
  "fiscal_year_ending_in_june_" : "2012",
  "filed_violation_count" : "121",
  "violation_type" : "Technical",
  "borough" : "Manhattan"
}
, {
  "fiscal_year_ending_in_june_" : "2013",
  "filed_violation_count" : "127",
  "violation_type" : "Technical",
  "borough" : "Manhattan"
}
, {
  "fiscal_year_ending_in_june_" : "2014",
  "filed_violation_count" : "113",
  "violation_type" : "Technical",
  "borough" : "Manhattan"
}
, {
  "fiscal_year_ending_in_june_" : "2015",
  "filed_violation_count" : "91",
  "violation_type" : "Technical",
  "borough" : "Manhattan"
}
, {
  "fiscal_year_ending_in_june_" : "2016",
  "filed_violation_count" : "107",
  "violation_type" : "Technical",
  "borough" : "Manhattan"
}
, {
  "fiscal_year_ending_in_june_" : "2006",
  "filed_violation_count" : "132",
  "violation_type" : "Absconder",
  "borough" : "Queens"
}
, {
  "fiscal_year_ending_in_june_" : "2007",
  "filed_violation_count" : "161",
  "violation_type" : "Absconder",
  "borough" : "Queens"
}
, {
  "fiscal_year_ending_in_june_" : "2008",
  "filed_violation_count" : "149",
  "violation_type" : "Absconder",
  "borough" : "Queens"
}
, {
  "fiscal_year_ending_in_june_" : "2009",
  "filed_violation_count" : "128",
  "violation_type" : "Absconder",
  "borough" : "Queens"
}
, {
  "fiscal_year_ending_in_june_" : "2010",
  "filed_violation_count" : "110",
  "violation_type" : "Absconder",
  "borough" : "Queens"
}
, {
  "fiscal_year_ending_in_june_" : "2011",
  "filed_violation_count" : "80",
  "violation_type" : "Absconder",
  "borough" : "Queens"
}
, {
  "fiscal_year_ending_in_june_" : "2012",
  "filed_violation_count" : "71",
  "violation_type" : "Absconder",
  "borough" : "Queens"
}
, {
  "fiscal_year_ending_in_june_" : "2013",
  "filed_violation_count" : "64",
  "violation_type" : "Absconder",
  "borough" : "Queens"
}
, {
  "fiscal_year_ending_in_june_" : "2014",
  "filed_violation_count" : "54",
  "violation_type" : "Absconder",
  "borough" : "Queens"
}
, {
  "fiscal_year_ending_in_june_" : "2015",
  "filed_violation_count" : "42",
  "violation_type" : "Absconder",
  "borough" : "Queens"
}
, {
  "fiscal_year_ending_in_june_" : "2016",
  "filed_violation_count" : "48",
  "violation_type" : "Absconder",
  "borough" : "Queens"
}
, {
  "fiscal_year_ending_in_june_" : "2006",
  "filed_violation_count" : "1182",
  "violation_type" : "Rearrests",
  "borough" : "Queens"
}
, {
  "fiscal_year_ending_in_june_" : "2007",
  "filed_violation_count" : "1291",
  "violation_type" : "Rearrests",
  "borough" : "Queens"
}
, {
  "fiscal_year_ending_in_june_" : "2008",
  "filed_violation_count" : "1287",
  "violation_type" : "Rearrests",
  "borough" : "Queens"
}
, {
  "fiscal_year_ending_in_june_" : "2009",
  "filed_violation_count" : "1048",
  "violation_type" : "Rearrests",
  "borough" : "Queens"
}
, {
  "fiscal_year_ending_in_june_" : "2010",
  "filed_violation_count" : "791",
  "violation_type" : "Rearrests",
  "borough" : "Queens"
}
, {
  "fiscal_year_ending_in_june_" : "2011",
  "filed_violation_count" : "574",
  "violation_type" : "Rearrests",
  "borough" : "Queens"
}
, {
  "fiscal_year_ending_in_june_" : "2012",
  "filed_violation_count" : "453",
  "violation_type" : "Rearrests",
  "borough" : "Queens"
}
, {
  "fiscal_year_ending_in_june_" : "2013",
  "filed_violation_count" : "448",
  "violation_type" : "Rearrests",
  "borough" : "Queens"
}
, {
  "fiscal_year_ending_in_june_" : "2014",
  "filed_violation_count" : "424",
  "violation_type" : "Rearrests",
  "borough" : "Queens"
}
, {
  "fiscal_year_ending_in_june_" : "2015",
  "filed_violation_count" : "360",
  "violation_type" : "Rearrests",
  "borough" : "Queens"
}
, {
  "fiscal_year_ending_in_june_" : "2016",
  "filed_violation_count" : "431",
  "violation_type" : "Rearrests",
  "borough" : "Queens"
}
, {
  "fiscal_year_ending_in_june_" : "2006",
  "filed_violation_count" : "307",
  "violation_type" : "Technical",
  "borough" : "Queens"
}
, {
  "fiscal_year_ending_in_june_" : "2007",
  "filed_violation_count" : "343",
  "violation_type" : "Technical",
  "borough" : "Queens"
}
, {
  "fiscal_year_ending_in_june_" : "2008",
  "filed_violation_count" : "349",
  "violation_type" : "Technical",
  "borough" : "Queens"
}
, {
  "fiscal_year_ending_in_june_" : "2009",
  "filed_violation_count" : "334",
  "violation_type" : "Technical",
  "borough" : "Queens"
}
, {
  "fiscal_year_ending_in_june_" : "2010",
  "filed_violation_count" : "301",
  "violation_type" : "Technical",
  "borough" : "Queens"
}
, {
  "fiscal_year_ending_in_june_" : "2011",
  "filed_violation_count" : "174",
  "violation_type" : "Technical",
  "borough" : "Queens"
}
, {
  "fiscal_year_ending_in_june_" : "2012",
  "filed_violation_count" : "123",
  "violation_type" : "Technical",
  "borough" : "Queens"
}
, {
  "fiscal_year_ending_in_june_" : "2013",
  "filed_violation_count" : "130",
  "violation_type" : "Technical",
  "borough" : "Queens"
}
, {
  "fiscal_year_ending_in_june_" : "2014",
  "filed_violation_count" : "153",
  "violation_type" : "Technical",
  "borough" : "Queens"
}
, {
  "fiscal_year_ending_in_june_" : "2015",
  "filed_violation_count" : "83",
  "violation_type" : "Technical",
  "borough" : "Queens"
}
, {
  "fiscal_year_ending_in_june_" : "2016",
  "filed_violation_count" : "84",
  "violation_type" : "Technical",
  "borough" : "Queens"
}
, {
  "fiscal_year_ending_in_june_" : "2006",
  "filed_violation_count" : "15",
  "violation_type" : "Absconder",
  "borough" : "Staten Island"
}
, {
  "fiscal_year_ending_in_june_" : "2007",
  "filed_violation_count" : "9",
  "violation_type" : "Absconder",
  "borough" : "Staten Island"
}
, {
  "fiscal_year_ending_in_june_" : "2008",
  "filed_violation_count" : "35",
  "violation_type" : "Absconder",
  "borough" : "Staten Island"
}
, {
  "fiscal_year_ending_in_june_" : "2009",
  "filed_violation_count" : "11",
  "violation_type" : "Absconder",
  "borough" : "Staten Island"
}
, {
  "fiscal_year_ending_in_june_" : "2010",
  "filed_violation_count" : "23",
  "violation_type" : "Absconder",
  "borough" : "Staten Island"
}
, {
  "fiscal_year_ending_in_june_" : "2011",
  "filed_violation_count" : "21",
  "violation_type" : "Absconder",
  "borough" : "Staten Island"
}
, {
  "fiscal_year_ending_in_june_" : "2012",
  "filed_violation_count" : "28",
  "violation_type" : "Absconder",
  "borough" : "Staten Island"
}
, {
  "fiscal_year_ending_in_june_" : "2013",
  "filed_violation_count" : "31",
  "violation_type" : "Absconder",
  "borough" : "Staten Island"
}
, {
  "fiscal_year_ending_in_june_" : "2014",
  "filed_violation_count" : "17",
  "violation_type" : "Absconder",
  "borough" : "Staten Island"
}
, {
  "fiscal_year_ending_in_june_" : "2015",
  "filed_violation_count" : "36",
  "violation_type" : "Absconder",
  "borough" : "Staten Island"
}
, {
  "fiscal_year_ending_in_june_" : "2016",
  "filed_violation_count" : "40",
  "violation_type" : "Absconder",
  "borough" : "Staten Island"
}
, {
  "fiscal_year_ending_in_june_" : "2006",
  "filed_violation_count" : "199",
  "violation_type" : "Rearrests",
  "borough" : "Staten Island"
}
, {
  "fiscal_year_ending_in_june_" : "2007",
  "filed_violation_count" : "146",
  "violation_type" : "Rearrests",
  "borough" : "Staten Island"
}
, {
  "fiscal_year_ending_in_june_" : "2008",
  "filed_violation_count" : "198",
  "violation_type" : "Rearrests",
  "borough" : "Staten Island"
}
, {
  "fiscal_year_ending_in_june_" : "2009",
  "filed_violation_count" : "206",
  "violation_type" : "Rearrests",
  "borough" : "Staten Island"
}
, {
  "fiscal_year_ending_in_june_" : "2010",
  "filed_violation_count" : "220",
  "violation_type" : "Rearrests",
  "borough" : "Staten Island"
}
, {
  "fiscal_year_ending_in_june_" : "2011",
  "filed_violation_count" : "107",
  "violation_type" : "Rearrests",
  "borough" : "Staten Island"
}
, {
  "fiscal_year_ending_in_june_" : "2012",
  "filed_violation_count" : "80",
  "violation_type" : "Rearrests",
  "borough" : "Staten Island"
}
, {
  "fiscal_year_ending_in_june_" : "2013",
  "filed_violation_count" : "83",
  "violation_type" : "Rearrests",
  "borough" : "Staten Island"
}
, {
  "fiscal_year_ending_in_june_" : "2014",
  "filed_violation_count" : "85",
  "violation_type" : "Rearrests",
  "borough" : "Staten Island"
}
, {
  "fiscal_year_ending_in_june_" : "2015",
  "filed_violation_count" : "122",
  "violation_type" : "Rearrests",
  "borough" : "Staten Island"
}
, {
  "fiscal_year_ending_in_june_" : "2016",
  "filed_violation_count" : "114",
  "violation_type" : "Rearrests",
  "borough" : "Staten Island"
}
, {
  "fiscal_year_ending_in_june_" : "2006",
  "filed_violation_count" : "78",
  "violation_type" : "Technical",
  "borough" : "Staten Island"
}
, {
  "fiscal_year_ending_in_june_" : "2007",
  "filed_violation_count" : "79",
  "violation_type" : "Technical",
  "borough" : "Staten Island"
}
, {
  "fiscal_year_ending_in_june_" : "2008",
  "filed_violation_count" : "71",
  "violation_type" : "Technical",
  "borough" : "Staten Island"
}
, {
  "fiscal_year_ending_in_june_" : "2009",
  "filed_violation_count" : "70",
  "violation_type" : "Technical",
  "borough" : "Staten Island"
}
, {
  "fiscal_year_ending_in_june_" : "2010",
  "filed_violation_count" : "96",
  "violation_type" : "Technical",
  "borough" : "Staten Island"
}
, {
  "fiscal_year_ending_in_june_" : "2011",
  "filed_violation_count" : "25",
  "violation_type" : "Technical",
  "borough" : "Staten Island"
}
, {
  "fiscal_year_ending_in_june_" : "2012",
  "filed_violation_count" : "12",
  "violation_type" : "Technical",
  "borough" : "Staten Island"
}
, {
  "fiscal_year_ending_in_june_" : "2013",
  "filed_violation_count" : "16",
  "violation_type" : "Technical",
  "borough" : "Staten Island"
}
, {
  "fiscal_year_ending_in_june_" : "2014",
  "filed_violation_count" : "5",
  "violation_type" : "Technical",
  "borough" : "Staten Island"
}
, {
  "fiscal_year_ending_in_june_" : "2015",
  "filed_violation_count" : "4",
  "violation_type" : "Technical",
  "borough" : "Staten Island"
}
, {
  "fiscal_year_ending_in_june_" : "2016",
  "filed_violation_count" : "10",
  "violation_type" : "Technical",
  "borough" : "Staten Island"
}
 ]