[ {
  "_nypd_population_2009" : "64.00",
  "_number_of_officers_5" : "199",
  "_number_of_officers_1" : "240",
  "_nypd_population_2005" : "64.80",
  "_number_of_officers_2" : "248",
  "_nypd_population_2006" : "65.70",
  "_number_of_officers_3" : "212",
  "_nypd_population_2007" : "65.80",
  "_number_of_officers_4" : "134",
  "_nypd_population_2008" : "65.00",
  "_percent_of_subtotal_2" : "71.50",
  "_percent_of_subtotal_3" : "70.90",
  "_percent_of_subtotal_1" : "65.00",
  "rank" : "Police officer",
  "_percent_of_subtotal_4" : "61.20",
  "_percent_of_subtotal_5" : "72.40"
}
, {
  "_nypd_population_2009" : "9.40",
  "_number_of_officers_5" : "11",
  "_number_of_officers_1" : "40",
  "_nypd_population_2005" : "10.50",
  "_number_of_officers_2" : "30",
  "_nypd_population_2006" : "9.30",
  "_number_of_officers_3" : "17",
  "_nypd_population_2007" : "8.70",
  "_number_of_officers_4" : "26",
  "_nypd_population_2008" : "9.00",
  "_percent_of_subtotal_2" : "8.60",
  "_percent_of_subtotal_3" : "5.70",
  "_percent_of_subtotal_1" : "10.80",
  "rank" : "Detective 3",
  "_percent_of_subtotal_4" : "11.90",
  "_percent_of_subtotal_5" : "4.00"
}
, {
  "_nypd_population_2009" : "3.10",
  "_number_of_officers_5" : "3",
  "_number_of_officers_1" : "0",
  "_nypd_population_2005" : "1.80",
  "_number_of_officers_2" : "3",
  "_nypd_population_2006" : "2.20",
  "_number_of_officers_3" : "1",
  "_nypd_population_2007" : "2.60",
  "_number_of_officers_4" : "4",
  "_nypd_population_2008" : "3.00",
  "_percent_of_subtotal_2" : "0.90",
  "_percent_of_subtotal_3" : "0.30",
  "_percent_of_subtotal_1" : "0.00",
  "rank" : "Detective 2",
  "_percent_of_subtotal_4" : "1.80",
  "_percent_of_subtotal_5" : "1.10"
}
, {
  "_nypd_population_2009" : "1.10",
  "_number_of_officers_5" : "0",
  "_number_of_officers_1" : "0",
  "_nypd_population_2005" : "0.60",
  "_number_of_officers_2" : "1",
  "_nypd_population_2006" : "0.80",
  "_number_of_officers_3" : "1",
  "_nypd_population_2007" : "0.90",
  "_number_of_officers_4" : "0",
  "_nypd_population_2008" : "1.00",
  "_percent_of_subtotal_2" : "0.30",
  "_percent_of_subtotal_3" : "0.30",
  "_percent_of_subtotal_1" : "0.00",
  "rank" : "Detective 1",
  "_percent_of_subtotal_4" : "0.00",
  "_percent_of_subtotal_5" : "0.00"
}
, {
  "_nypd_population_2009" : "1.80",
  "_number_of_officers_5" : "1",
  "_number_of_officers_1" : "6",
  "_nypd_population_2005" : "1.70",
  "_number_of_officers_2" : "3",
  "_nypd_population_2006" : "1.60",
  "_number_of_officers_3" : "2",
  "_nypd_population_2007" : "1.70",
  "_number_of_officers_4" : "0",
  "_nypd_population_2008" : "1.70",
  "_percent_of_subtotal_2" : "0.90",
  "_percent_of_subtotal_3" : "0.70",
  "_percent_of_subtotal_1" : "1.60",
  "rank" : "Detective specialist",
  "_percent_of_subtotal_4" : "0.00",
  "_percent_of_subtotal_5" : "0.40"
}
, {
  "_nypd_population_2009" : "13.50",
  "_number_of_officers_5" : "50",
  "_number_of_officers_1" : "65",
  "_nypd_population_2005" : "13.50",
  "_number_of_officers_2" : "48",
  "_nypd_population_2006" : "13.30",
  "_number_of_officers_3" : "51",
  "_nypd_population_2007" : "12.90",
  "_number_of_officers_4" : "40",
  "_nypd_population_2008" : "13.20",
  "_percent_of_subtotal_2" : "13.80",
  "_percent_of_subtotal_3" : "17.10",
  "_percent_of_subtotal_1" : "17.60",
  "rank" : "Sergeant",
  "_percent_of_subtotal_4" : "18.30",
  "_percent_of_subtotal_5" : "18.20"
}
, {
  "_nypd_population_2009" : "4.60",
  "_number_of_officers_5" : "11",
  "_number_of_officers_1" : "14",
  "_nypd_population_2005" : "4.70",
  "_number_of_officers_2" : "11",
  "_nypd_population_2006" : "4.70",
  "_number_of_officers_3" : "11",
  "_nypd_population_2007" : "4.80",
  "_number_of_officers_4" : "12",
  "_nypd_population_2008" : "4.80",
  "_percent_of_subtotal_2" : "3.20",
  "_percent_of_subtotal_3" : "3.70",
  "_percent_of_subtotal_1" : "3.80",
  "rank" : "Lieutenant",
  "_percent_of_subtotal_4" : "5.50",
  "_percent_of_subtotal_5" : "4.00"
}
, {
  "_nypd_population_2009" : "0.40",
  "_number_of_officers_5" : "0",
  "_number_of_officers_1" : "1",
  "_nypd_population_2005" : "0.20",
  "_number_of_officers_2" : "0",
  "_nypd_population_2006" : "0.20",
  "_number_of_officers_3" : "0",
  "_nypd_population_2007" : "0.30",
  "_number_of_officers_4" : "0",
  "_nypd_population_2008" : "0.30",
  "_percent_of_subtotal_2" : "0.00",
  "_percent_of_subtotal_3" : "0.00",
  "_percent_of_subtotal_1" : "0.30",
  "rank" : "Lieutenant commander detective",
  "_percent_of_subtotal_4" : "0.00",
  "_percent_of_subtotal_5" : "0.00"
}
, {
  "_nypd_population_2009" : "1.20",
  "_number_of_officers_5" : "0",
  "_number_of_officers_1" : "3",
  "_nypd_population_2005" : "1.40",
  "_number_of_officers_2" : "1",
  "_nypd_population_2006" : "1.30",
  "_number_of_officers_3" : "2",
  "_nypd_population_2007" : "1.30",
  "_number_of_officers_4" : "3",
  "_nypd_population_2008" : "1.10",
  "_percent_of_subtotal_2" : "0.30",
  "_percent_of_subtotal_3" : "0.70",
  "_percent_of_subtotal_1" : "0.80",
  "rank" : "Captain",
  "_percent_of_subtotal_4" : "1.40",
  "_percent_of_subtotal_5" : "0.00"
}
, {
  "_nypd_population_2009" : "0.70",
  "_number_of_officers_5" : "0",
  "_number_of_officers_1" : "0",
  "_nypd_population_2005" : "0.70",
  "_number_of_officers_2" : "1",
  "_nypd_population_2006" : "0.70",
  "_number_of_officers_3" : "1",
  "_nypd_population_2007" : "0.80",
  "_number_of_officers_4" : "0",
  "_nypd_population_2008" : "0.70",
  "_percent_of_subtotal_2" : "0.30",
  "_percent_of_subtotal_3" : "0.30",
  "_percent_of_subtotal_1" : "0.00",
  "rank" : "Deputy Inspector/Inspector",
  "_percent_of_subtotal_4" : "0.00",
  "_percent_of_subtotal_5" : "0.00"
}
, {
  "_nypd_population_2009" : "0.20",
  "_number_of_officers_5" : "0",
  "_number_of_officers_1" : "0",
  "_nypd_population_2005" : "0.10",
  "_number_of_officers_2" : "1",
  "_nypd_population_2006" : "0.20",
  "_number_of_officers_3" : "1",
  "_nypd_population_2007" : "0.20",
  "_number_of_officers_4" : "0",
  "_nypd_population_2008" : "0.20",
  "_percent_of_subtotal_2" : "0.30",
  "_percent_of_subtotal_3" : "0.30",
  "_percent_of_subtotal_1" : "0.00",
  "rank" : "Other ranks",
  "_percent_of_subtotal_4" : "0.00",
  "_percent_of_subtotal_5" : "0.00"
}
, {
  "_nypd_population_2009" : "100.00",
  "_number_of_officers_5" : "275",
  "_number_of_officers_1" : "369",
  "_nypd_population_2005" : "100.00",
  "_number_of_officers_2" : "347",
  "_nypd_population_2006" : "100.00",
  "_number_of_officers_3" : "299",
  "_nypd_population_2007" : "100.00",
  "_number_of_officers_4" : "219",
  "_nypd_population_2008" : "100.00",
  "_percent_of_subtotal_2" : "100.00",
  "_percent_of_subtotal_3" : "100.00",
  "_percent_of_subtotal_1" : "100.00",
  "rank" : "Subtotal",
  "_percent_of_subtotal_4" : "100.00",
  "_percent_of_subtotal_5" : "100.00"
}
, {
  "_number_of_officers_5" : "1",
  "_number_of_officers_1" : "2",
  "_number_of_officers_2" : "0",
  "_number_of_officers_3" : "1",
  "_number_of_officers_4" : "0",
  "rank" : "Officer unidentified"
}
, {
  "_number_of_officers_5" : "276",
  "_number_of_officers_1" : "371",
  "_number_of_officers_2" : "347",
  "_number_of_officers_3" : "300",
  "_number_of_officers_4" : "219",
  "rank" : "Total"
}
, { }
 ]