[ {
  "fy_2006_actual" : "59555",
  "fy_2007_actual" : "63384",
  "agency_name" : "Mayoralty",
  "fy_2008_actual" : "63791",
  "fy_2021_plan" : "94741",
  "fy_2004_actual" : "54292",
  "fy_2005_actual" : "56651",
  "fy_2020_plan" : "94741",
  "agn" : "002",
  "fy_2017_plan" : "88573",
  "fy_2019_plan" : "98747",
  "fy_2018_plan" : "100479",
  "fy_2011_actual" : "63616",
  "fy_2002_actual" : "67815",
  "fy_2003_actual" : "50729",
  "fy_2009_actual" : "66374",
  "fy_2013_actual" : "60937",
  "fy_2010_actual" : "67427",
  "fy_2012_actual" : "61147",
  "fy_2014_actual" : "66073",
  "fy_2015_actual" : "69635",
  "fy_2016_actual" : "70820"
}
, {
  "fy_2006_actual" : "63297",
  "fy_2007_actual" : "71748",
  "agency_name" : "Board of Elections",
  "fy_2008_actual" : "80676",
  "fy_2021_plan" : "94370",
  "fy_2004_actual" : "68059",
  "fy_2005_actual" : "59788",
  "fy_2020_plan" : "96564",
  "agn" : "003",
  "fy_2017_plan" : "130099",
  "fy_2019_plan" : "95113",
  "fy_2018_plan" : "140996",
  "fy_2011_actual" : "101470",
  "fy_2002_actual" : "67482",
  "fy_2003_actual" : "47642",
  "fy_2009_actual" : "80749",
  "fy_2013_actual" : "101415",
  "fy_2010_actual" : "95446",
  "fy_2012_actual" : "109376",
  "fy_2014_actual" : "115523",
  "fy_2015_actual" : "106508",
  "fy_2016_actual" : "116586"
}
, {
  "fy_2006_actual" : "38692",
  "fy_2007_actual" : "6576",
  "agency_name" : "Campaign Finance Board",
  "fy_2008_actual" : "6497",
  "fy_2021_plan" : "14019",
  "fy_2004_actual" : "14196",
  "fy_2005_actual" : "5357",
  "fy_2020_plan" : "14019",
  "agn" : "004",
  "fy_2017_plan" : "16206",
  "fy_2019_plan" : "14019",
  "fy_2018_plan" : "56661",
  "fy_2011_actual" : "11279",
  "fy_2002_actual" : "48478",
  "fy_2003_actual" : "7245",
  "fy_2009_actual" : "8658",
  "fy_2013_actual" : "9691",
  "fy_2010_actual" : "44320",
  "fy_2012_actual" : "9645",
  "fy_2014_actual" : "53476",
  "fy_2015_actual" : "10647",
  "fy_2016_actual" : "7886"
}
, {
  "fy_2006_actual" : "4944",
  "fy_2007_actual" : "4539",
  "agency_name" : "Office of the Actuary",
  "fy_2008_actual" : "5060",
  "fy_2021_plan" : "7354",
  "fy_2004_actual" : "3594",
  "fy_2005_actual" : "4116",
  "fy_2020_plan" : "7354",
  "agn" : "008",
  "fy_2017_plan" : "7194",
  "fy_2019_plan" : "7354",
  "fy_2018_plan" : "7251",
  "fy_2011_actual" : "4997",
  "fy_2002_actual" : "3149",
  "fy_2003_actual" : "3277",
  "fy_2009_actual" : "4689",
  "fy_2013_actual" : "5704",
  "fy_2010_actual" : "4977",
  "fy_2012_actual" : "5547",
  "fy_2014_actual" : "5568",
  "fy_2015_actual" : "6247",
  "fy_2016_actual" : "6694"
}
, {
  "fy_2006_actual" : "4318",
  "fy_2007_actual" : "4462",
  "agency_name" : "President,Borough of Manhattan",
  "fy_2008_actual" : "5110",
  "fy_2021_plan" : "4589",
  "fy_2004_actual" : "3634",
  "fy_2005_actual" : "3889",
  "fy_2020_plan" : "4589",
  "agn" : "010",
  "fy_2017_plan" : "4839",
  "fy_2019_plan" : "4589",
  "fy_2018_plan" : "5021",
  "fy_2011_actual" : "3612",
  "fy_2002_actual" : "5023",
  "fy_2003_actual" : "3778",
  "fy_2009_actual" : "4979",
  "fy_2013_actual" : "4430",
  "fy_2010_actual" : "4350",
  "fy_2012_actual" : "4541",
  "fy_2014_actual" : "4070",
  "fy_2015_actual" : "4425",
  "fy_2016_actual" : "4661"
}
, {
  "fy_2006_actual" : "5345",
  "fy_2007_actual" : "6180",
  "agency_name" : "President,Borough of the Bronx",
  "fy_2008_actual" : "6429",
  "fy_2021_plan" : "5459",
  "fy_2004_actual" : "4854",
  "fy_2005_actual" : "5199",
  "fy_2020_plan" : "5459",
  "agn" : "011",
  "fy_2017_plan" : "5778",
  "fy_2019_plan" : "5459",
  "fy_2018_plan" : "6017",
  "fy_2011_actual" : "4841",
  "fy_2002_actual" : "6944",
  "fy_2003_actual" : "5283",
  "fy_2009_actual" : "5192",
  "fy_2013_actual" : "4854",
  "fy_2010_actual" : "4849",
  "fy_2012_actual" : "4825",
  "fy_2014_actual" : "4796",
  "fy_2015_actual" : "5172",
  "fy_2016_actual" : "5047"
}
, {
  "fy_2006_actual" : "5258",
  "fy_2007_actual" : "6049",
  "agency_name" : "President,Borough of Brooklyn",
  "fy_2008_actual" : "7981",
  "fy_2021_plan" : "5702",
  "fy_2004_actual" : "4713",
  "fy_2005_actual" : "5053",
  "fy_2020_plan" : "5702",
  "agn" : "012",
  "fy_2017_plan" : "6323",
  "fy_2019_plan" : "5702",
  "fy_2018_plan" : "6690",
  "fy_2011_actual" : "5150",
  "fy_2002_actual" : "5941",
  "fy_2003_actual" : "4857",
  "fy_2009_actual" : "5618",
  "fy_2013_actual" : "5086",
  "fy_2010_actual" : "5190",
  "fy_2012_actual" : "5134",
  "fy_2014_actual" : "4916",
  "fy_2015_actual" : "5421",
  "fy_2016_actual" : "5936"
}
, {
  "fy_2006_actual" : "4831",
  "fy_2007_actual" : "5529",
  "agency_name" : "President,Borough of Queens",
  "fy_2008_actual" : "6620",
  "fy_2021_plan" : "4749",
  "fy_2004_actual" : "4505",
  "fy_2005_actual" : "4719",
  "fy_2020_plan" : "4749",
  "agn" : "013",
  "fy_2017_plan" : "5270",
  "fy_2019_plan" : "4749",
  "fy_2018_plan" : "5585",
  "fy_2011_actual" : "4639",
  "fy_2002_actual" : "6042",
  "fy_2003_actual" : "4553",
  "fy_2009_actual" : "4717",
  "fy_2013_actual" : "4533",
  "fy_2010_actual" : "4588",
  "fy_2012_actual" : "4587",
  "fy_2014_actual" : "4931",
  "fy_2015_actual" : "4678",
  "fy_2016_actual" : "4981"
}
, {
  "fy_2006_actual" : "4018",
  "fy_2007_actual" : "4267",
  "agency_name" : "President,Borough of S.I.",
  "fy_2008_actual" : "4679",
  "fy_2021_plan" : "4248",
  "fy_2004_actual" : "3602",
  "fy_2005_actual" : "3769",
  "fy_2020_plan" : "4248",
  "agn" : "014",
  "fy_2017_plan" : "4429",
  "fy_2019_plan" : "4248",
  "fy_2018_plan" : "4555",
  "fy_2011_actual" : "3769",
  "fy_2002_actual" : "4742",
  "fy_2003_actual" : "3686",
  "fy_2009_actual" : "3946",
  "fy_2013_actual" : "3905",
  "fy_2010_actual" : "3871",
  "fy_2012_actual" : "3859",
  "fy_2014_actual" : "4130",
  "fy_2015_actual" : "3777",
  "fy_2016_actual" : "4048"
}
, {
  "fy_2006_actual" : "53673",
  "fy_2007_actual" : "55102",
  "agency_name" : "Office of the Comptroller",
  "fy_2008_actual" : "56906",
  "fy_2021_plan" : "81253",
  "fy_2004_actual" : "50200",
  "fy_2005_actual" : "50290",
  "fy_2020_plan" : "81253",
  "agn" : "015",
  "fy_2017_plan" : "80772",
  "fy_2019_plan" : "81253",
  "fy_2018_plan" : "81249",
  "fy_2011_actual" : "53504",
  "fy_2002_actual" : "54474",
  "fy_2003_actual" : "52230",
  "fy_2009_actual" : "58646",
  "fy_2013_actual" : "56386",
  "fy_2010_actual" : "55041",
  "fy_2012_actual" : "55290",
  "fy_2014_actual" : "64282",
  "fy_2015_actual" : "69988",
  "fy_2016_actual" : "70935"
}
, {
  "fy_2006_actual" : "4047",
  "fy_2007_actual" : "6244",
  "agency_name" : "Dept. of Emergency Management",
  "fy_2008_actual" : "9882",
  "fy_2021_plan" : "27210",
  "fy_2004_actual" : "3481",
  "fy_2005_actual" : "3420",
  "fy_2020_plan" : "26294",
  "agn" : "017",
  "fy_2017_plan" : "28101",
  "fy_2019_plan" : "26360",
  "fy_2018_plan" : "35293",
  "fy_2011_actual" : "4155",
  "fy_2002_actual" : "0",
  "fy_2003_actual" : "3633",
  "fy_2009_actual" : "10905",
  "fy_2013_actual" : "15717",
  "fy_2010_actual" : "13051",
  "fy_2012_actual" : "5605",
  "fy_2014_actual" : "7464",
  "fy_2015_actual" : "20556",
  "fy_2016_actual" : "3352"
}
, {
  "fy_2006_actual" : "2366",
  "fy_2007_actual" : "2601",
  "agency_name" : "Office of Administrative Tax Appeals",
  "fy_2008_actual" : "3072",
  "fy_2021_plan" : "5063",
  "fy_2004_actual" : "1956",
  "fy_2005_actual" : "2319",
  "fy_2020_plan" : "5063",
  "agn" : "021",
  "fy_2017_plan" : "4973",
  "fy_2019_plan" : "5063",
  "fy_2018_plan" : "4946",
  "fy_2011_actual" : "3712",
  "fy_2002_actual" : "1992",
  "fy_2003_actual" : "1879",
  "fy_2009_actual" : "3987",
  "fy_2013_actual" : "4247",
  "fy_2010_actual" : "3707",
  "fy_2012_actual" : "3850",
  "fy_2014_actual" : "4162",
  "fy_2015_actual" : "4261",
  "fy_2016_actual" : "4259"
}
, {
  "fy_2006_actual" : "116962",
  "fy_2007_actual" : "119418",
  "agency_name" : "Law Department",
  "fy_2008_actual" : "118905",
  "fy_2021_plan" : "199475",
  "fy_2004_actual" : "103228",
  "fy_2005_actual" : "112207",
  "fy_2020_plan" : "199475",
  "agn" : "025",
  "fy_2017_plan" : "208916",
  "fy_2019_plan" : "197855",
  "fy_2018_plan" : "201687",
  "fy_2011_actual" : "124860",
  "fy_2002_actual" : "89579",
  "fy_2003_actual" : "96008",
  "fy_2009_actual" : "125096",
  "fy_2013_actual" : "133540",
  "fy_2010_actual" : "130300",
  "fy_2012_actual" : "127491",
  "fy_2014_actual" : "152241",
  "fy_2015_actual" : "165831",
  "fy_2016_actual" : "183601"
}
, {
  "fy_2006_actual" : "7536",
  "fy_2007_actual" : "7564",
  "agency_name" : "Department of City Planning",
  "fy_2008_actual" : "9433",
  "fy_2021_plan" : "25616",
  "fy_2004_actual" : "4544",
  "fy_2005_actual" : "6779",
  "fy_2020_plan" : "25616",
  "agn" : "030",
  "fy_2017_plan" : "24281",
  "fy_2019_plan" : "26251",
  "fy_2018_plan" : "32822",
  "fy_2011_actual" : "7943",
  "fy_2002_actual" : "6581",
  "fy_2003_actual" : "7706",
  "fy_2009_actual" : "10801",
  "fy_2013_actual" : "6934",
  "fy_2010_actual" : "10704",
  "fy_2012_actual" : "8233",
  "fy_2014_actual" : "6889",
  "fy_2015_actual" : "9976",
  "fy_2016_actual" : "16169"
}
, {
  "fy_2006_actual" : "16723",
  "fy_2007_actual" : "16975",
  "agency_name" : "Department of Investigation",
  "fy_2008_actual" : "18252",
  "fy_2021_plan" : "32401",
  "fy_2004_actual" : "16245",
  "fy_2005_actual" : "16116",
  "fy_2020_plan" : "32401",
  "agn" : "032",
  "fy_2017_plan" : "30270",
  "fy_2019_plan" : "32401",
  "fy_2018_plan" : "31535",
  "fy_2011_actual" : "15431",
  "fy_2002_actual" : "20792",
  "fy_2003_actual" : "18441",
  "fy_2009_actual" : "17144",
  "fy_2013_actual" : "15237",
  "fy_2010_actual" : "16734",
  "fy_2012_actual" : "14522",
  "fy_2014_actual" : "17350",
  "fy_2015_actual" : "20851",
  "fy_2016_actual" : "24723"
}
, {
  "fy_2006_actual" : "19034",
  "fy_2007_actual" : "20087",
  "agency_name" : "NY Public Library - Research",
  "fy_2008_actual" : "24326",
  "fy_2021_plan" : "27993",
  "fy_2004_actual" : "16967",
  "fy_2005_actual" : "18154",
  "fy_2020_plan" : "27993",
  "agn" : "035",
  "fy_2017_plan" : "27811",
  "fy_2019_plan" : "27993",
  "fy_2018_plan" : "28043",
  "fy_2011_actual" : "22023",
  "fy_2002_actual" : "18698",
  "fy_2003_actual" : "16633",
  "fy_2009_actual" : "24974",
  "fy_2013_actual" : "22278",
  "fy_2010_actual" : "26642",
  "fy_2012_actual" : "22004",
  "fy_2014_actual" : "22747",
  "fy_2015_actual" : "24266",
  "fy_2016_actual" : "26737"
}
, {
  "fy_2006_actual" : "96464",
  "fy_2007_actual" : "106357",
  "agency_name" : "New York Public Library",
  "fy_2008_actual" : "117198",
  "fy_2021_plan" : "137233",
  "fy_2004_actual" : "89747",
  "fy_2005_actual" : "94737",
  "fy_2020_plan" : "137233",
  "agn" : "037",
  "fy_2017_plan" : "137063",
  "fy_2019_plan" : "137233",
  "fy_2018_plan" : "137698",
  "fy_2011_actual" : "110653",
  "fy_2002_actual" : "96805",
  "fy_2003_actual" : "87471",
  "fy_2009_actual" : "121222",
  "fy_2013_actual" : "111016",
  "fy_2010_actual" : "114287",
  "fy_2012_actual" : "110658",
  "fy_2014_actual" : "112616",
  "fy_2015_actual" : "119243",
  "fy_2016_actual" : "132780"
}
, {
  "fy_2006_actual" : "73841",
  "fy_2007_actual" : "78775",
  "agency_name" : "Brooklyn Public Library",
  "fy_2008_actual" : "87277",
  "fy_2021_plan" : "102002",
  "fy_2004_actual" : "66781",
  "fy_2005_actual" : "70286",
  "fy_2020_plan" : "102002",
  "agn" : "038",
  "fy_2017_plan" : "101766",
  "fy_2019_plan" : "102002",
  "fy_2018_plan" : "102412",
  "fy_2011_actual" : "81956",
  "fy_2002_actual" : "71464",
  "fy_2003_actual" : "64665",
  "fy_2009_actual" : "90495",
  "fy_2013_actual" : "82707",
  "fy_2010_actual" : "85427",
  "fy_2012_actual" : "83698",
  "fy_2014_actual" : "83573",
  "fy_2015_actual" : "89402",
  "fy_2016_actual" : "99090"
}
, {
  "fy_2006_actual" : "71802",
  "fy_2007_actual" : "76770",
  "agency_name" : "Queens Borough Public Library",
  "fy_2008_actual" : "85671",
  "fy_2021_plan" : "104530",
  "fy_2004_actual" : "63095",
  "fy_2005_actual" : "66834",
  "fy_2020_plan" : "104530",
  "agn" : "039",
  "fy_2017_plan" : "103491",
  "fy_2019_plan" : "104530",
  "fy_2018_plan" : "104548",
  "fy_2011_actual" : "80988",
  "fy_2002_actual" : "68140",
  "fy_2003_actual" : "61571",
  "fy_2009_actual" : "88576",
  "fy_2013_actual" : "81871",
  "fy_2010_actual" : "83940",
  "fy_2012_actual" : "82519",
  "fy_2014_actual" : "83731",
  "fy_2015_actual" : "89179",
  "fy_2016_actual" : "100505"
}
, {
  "fy_2006_actual" : "6306405",
  "fy_2007_actual" : "6779894",
  "agency_name" : "Department of Education",
  "fy_2008_actual" : "6997793",
  "fy_2021_plan" : "12949305",
  "fy_2004_actual" : "5464382",
  "fy_2005_actual" : "5605073",
  "fy_2020_plan" : "12588116",
  "agn" : "040",
  "fy_2017_plan" : "11119526",
  "fy_2019_plan" : "12358346",
  "fy_2018_plan" : "11648573",
  "fy_2011_actual" : "7737414",
  "fy_2002_actual" : "4784694",
  "fy_2003_actual" : "5103243",
  "fy_2009_actual" : "7259066",
  "fy_2013_actual" : "9080876",
  "fy_2010_actual" : "7140162",
  "fy_2012_actual" : "9075717",
  "fy_2014_actual" : "9546810",
  "fy_2015_actual" : "9739990",
  "fy_2016_actual" : "10607314"
}
, {
  "fy_2006_actual" : "394116",
  "fy_2007_actual" : "410674",
  "agency_name" : "City University",
  "fy_2008_actual" : "445361",
  "fy_2021_plan" : "848584",
  "fy_2004_actual" : "353139",
  "fy_2005_actual" : "374457",
  "fy_2020_plan" : "835431",
  "agn" : "042",
  "fy_2017_plan" : "807800",
  "fy_2019_plan" : "827851",
  "fy_2018_plan" : "829327",
  "fy_2011_actual" : "539276",
  "fy_2002_actual" : "287507",
  "fy_2003_actual" : "309476",
  "fy_2009_actual" : "481431",
  "fy_2013_actual" : "589995",
  "fy_2010_actual" : "528839",
  "fy_2012_actual" : "561417",
  "fy_2014_actual" : "621073",
  "fy_2015_actual" : "665084",
  "fy_2016_actual" : "703361"
}
, {
  "fy_2006_actual" : "10073",
  "fy_2007_actual" : "10717",
  "agency_name" : "Civilian Complaint Review Bd.",
  "fy_2008_actual" : "11074",
  "fy_2021_plan" : "16720",
  "fy_2004_actual" : "10054",
  "fy_2005_actual" : "9776",
  "fy_2020_plan" : "16720",
  "agn" : "054",
  "fy_2017_plan" : "16179",
  "fy_2019_plan" : "16720",
  "fy_2018_plan" : "16027",
  "fy_2011_actual" : "9623",
  "fy_2002_actual" : "9324",
  "fy_2003_actual" : "8874",
  "fy_2009_actual" : "11300",
  "fy_2013_actual" : "10408",
  "fy_2010_actual" : "10091",
  "fy_2012_actual" : "8739",
  "fy_2014_actual" : "11202",
  "fy_2015_actual" : "12684",
  "fy_2016_actual" : "14077"
}
, {
  "fy_2006_actual" : "3404713",
  "fy_2007_actual" : "3461451",
  "agency_name" : "Police Department",
  "fy_2008_actual" : "3734724",
  "fy_2021_plan" : "5188180",
  "fy_2004_actual" : "3218168",
  "fy_2005_actual" : "3463754",
  "fy_2020_plan" : "5218991",
  "agn" : "056",
  "fy_2017_plan" : "5072398",
  "fy_2019_plan" : "5225620",
  "fy_2018_plan" : "5188759",
  "fy_2011_actual" : "4260737",
  "fy_2002_actual" : "3099888",
  "fy_2003_actual" : "3158965",
  "fy_2009_actual" : "4057374",
  "fy_2013_actual" : "4283570",
  "fy_2010_actual" : "4199393",
  "fy_2012_actual" : "4336232",
  "fy_2014_actual" : "4372951",
  "fy_2015_actual" : "4618153",
  "fy_2016_actual" : "4799701"
}
, {
  "fy_2006_actual" : "1246047",
  "fy_2007_actual" : "1271686",
  "agency_name" : "Fire Department",
  "fy_2008_actual" : "1323216",
  "fy_2021_plan" : "1785199",
  "fy_2004_actual" : "1061562",
  "fy_2005_actual" : "1091062",
  "fy_2020_plan" : "1785745",
  "agn" : "057",
  "fy_2017_plan" : "1794870",
  "fy_2019_plan" : "1758886",
  "fy_2018_plan" : "1786931",
  "fy_2011_actual" : "1487887",
  "fy_2002_actual" : "1058706",
  "fy_2003_actual" : "1046649",
  "fy_2009_actual" : "1363732",
  "fy_2013_actual" : "1576578",
  "fy_2010_actual" : "1431240",
  "fy_2012_actual" : "1513063",
  "fy_2014_actual" : "1615875",
  "fy_2015_actual" : "1644394",
  "fy_2016_actual" : "1707700"
}
, {
  "fy_2006_actual" : "0",
  "fy_2007_actual" : "0",
  "agency_name" : "Department of Veterans' Services",
  "fy_2008_actual" : "0",
  "fy_2021_plan" : "4167",
  "fy_2004_actual" : "0",
  "fy_2005_actual" : "0",
  "fy_2020_plan" : "4167",
  "agn" : "063",
  "fy_2017_plan" : "3629",
  "fy_2019_plan" : "4167",
  "fy_2018_plan" : "4020",
  "fy_2011_actual" : "0",
  "fy_2002_actual" : "0",
  "fy_2003_actual" : "0",
  "fy_2009_actual" : "0",
  "fy_2013_actual" : "0",
  "fy_2010_actual" : "0",
  "fy_2012_actual" : "0",
  "fy_2014_actual" : "0",
  "fy_2015_actual" : "0",
  "fy_2016_actual" : "0"
}
, {
  "fy_2006_actual" : "684494",
  "fy_2007_actual" : "900507",
  "agency_name" : "Admin. for Children Services",
  "fy_2008_actual" : "830334",
  "fy_2021_plan" : "802525",
  "fy_2004_actual" : "579593",
  "fy_2005_actual" : "621522",
  "fy_2020_plan" : "799488",
  "agn" : "068",
  "fy_2017_plan" : "813526",
  "fy_2019_plan" : "788748",
  "fy_2018_plan" : "1023440",
  "fy_2011_actual" : "695156",
  "fy_2002_actual" : "652125",
  "fy_2003_actual" : "627243",
  "fy_2009_actual" : "817647",
  "fy_2013_actual" : "822186",
  "fy_2010_actual" : "710425",
  "fy_2012_actual" : "847576",
  "fy_2014_actual" : "861826",
  "fy_2015_actual" : "930146",
  "fy_2016_actual" : "924121"
}
, {
  "fy_2006_actual" : "4839573",
  "fy_2007_actual" : "5385637",
  "agency_name" : "Department of Social Services",
  "fy_2008_actual" : "6525557",
  "fy_2021_plan" : "7623053",
  "fy_2004_actual" : "4577482",
  "fy_2005_actual" : "5165384",
  "fy_2020_plan" : "7608926",
  "agn" : "069",
  "fy_2017_plan" : "7309357",
  "fy_2019_plan" : "7563769",
  "fy_2018_plan" : "7576314",
  "fy_2011_actual" : "5659488",
  "fy_2002_actual" : "3760680",
  "fy_2003_actual" : "3960255",
  "fy_2009_actual" : "6127839",
  "fy_2013_actual" : "7318762",
  "fy_2010_actual" : "6079792",
  "fy_2012_actual" : "7154813",
  "fy_2014_actual" : "7482195",
  "fy_2015_actual" : "7681477",
  "fy_2016_actual" : "7367844"
}
, {
  "fy_2006_actual" : "346841",
  "fy_2007_actual" : "347749",
  "agency_name" : "Dept. of Homeless Services",
  "fy_2008_actual" : "360226",
  "fy_2021_plan" : "911015",
  "fy_2004_actual" : "264615",
  "fy_2005_actual" : "301093",
  "fy_2020_plan" : "906352",
  "agn" : "071",
  "fy_2017_plan" : "1002237",
  "fy_2019_plan" : "898353",
  "fy_2018_plan" : "888633",
  "fy_2011_actual" : "417276",
  "fy_2002_actual" : "252190",
  "fy_2003_actual" : "285709",
  "fy_2009_actual" : "350281",
  "fy_2013_actual" : "472029",
  "fy_2010_actual" : "373743",
  "fy_2012_actual" : "427209",
  "fy_2014_actual" : "497070",
  "fy_2015_actual" : "680834",
  "fy_2016_actual" : "798076"
}
, {
  "fy_2006_actual" : "859822",
  "fy_2007_actual" : "913457",
  "agency_name" : "Department of Correction",
  "fy_2008_actual" : "926553",
  "fy_2021_plan" : "1452122",
  "fy_2004_actual" : "791570",
  "fy_2005_actual" : "778478",
  "fy_2020_plan" : "1441493",
  "agn" : "072",
  "fy_2017_plan" : "1371964",
  "fy_2019_plan" : "1425838",
  "fy_2018_plan" : "1434180",
  "fy_2011_actual" : "1020440",
  "fy_2002_actual" : "811611",
  "fy_2003_actual" : "822870",
  "fy_2009_actual" : "974990",
  "fy_2013_actual" : "1064109",
  "fy_2010_actual" : "975603",
  "fy_2012_actual" : "1058821",
  "fy_2014_actual" : "1088985",
  "fy_2015_actual" : "1148369",
  "fy_2016_actual" : "1293463"
}
, {
  "fy_2006_actual" : "861",
  "fy_2007_actual" : "886",
  "agency_name" : "Board of Correction",
  "fy_2008_actual" : "915",
  "fy_2021_plan" : "3003",
  "fy_2004_actual" : "855",
  "fy_2005_actual" : "830",
  "fy_2020_plan" : "3003",
  "agn" : "073",
  "fy_2017_plan" : "2644",
  "fy_2019_plan" : "3003",
  "fy_2018_plan" : "2836",
  "fy_2011_actual" : "929",
  "fy_2002_actual" : "906",
  "fy_2003_actual" : "830",
  "fy_2009_actual" : "904",
  "fy_2013_actual" : "1031",
  "fy_2010_actual" : "921",
  "fy_2012_actual" : "900",
  "fy_2014_actual" : "1632",
  "fy_2015_actual" : "1522",
  "fy_2016_actual" : "1489"
}
, {
  "fy_2006_actual" : "0",
  "fy_2007_actual" : "0",
  "agency_name" : "Department of Employment",
  "fy_2008_actual" : "0",
  "fy_2021_plan" : "0",
  "fy_2004_actual" : "0",
  "fy_2005_actual" : "0",
  "fy_2020_plan" : "0",
  "agn" : "094",
  "fy_2017_plan" : "0",
  "fy_2019_plan" : "0",
  "fy_2018_plan" : "0",
  "fy_2011_actual" : "0",
  "fy_2002_actual" : "10852",
  "fy_2003_actual" : "6988",
  "fy_2009_actual" : "0",
  "fy_2013_actual" : "0",
  "fy_2010_actual" : "0",
  "fy_2012_actual" : "0",
  "fy_2014_actual" : "0",
  "fy_2015_actual" : "0",
  "fy_2016_actual" : "0"
}
, {
  "fy_2006_actual" : "3837752",
  "fy_2007_actual" : "4688680",
  "agency_name" : "Citywide Pension Contributions",
  "fy_2008_actual" : "5570853",
  "fy_2021_plan" : "9860579",
  "fy_2004_actual" : "2263064",
  "fy_2005_actual" : "3194122",
  "fy_2020_plan" : "9798287",
  "agn" : "095",
  "fy_2017_plan" : "9250783",
  "fy_2019_plan" : "9726856",
  "fy_2018_plan" : "9427361",
  "fy_2011_actual" : "6834496",
  "fy_2002_actual" : "1334377",
  "fy_2003_actual" : "1533917",
  "fy_2009_actual" : "6217046",
  "fy_2013_actual" : "8022259",
  "fy_2010_actual" : "6583254",
  "fy_2012_actual" : "7797915",
  "fy_2014_actual" : "8109074",
  "fy_2015_actual" : "8457833",
  "fy_2016_actual" : "9138938"
}
, {
  "fy_2006_actual" : "5775998",
  "fy_2007_actual" : "6517244",
  "agency_name" : "Miscellaneous",
  "fy_2008_actual" : "5119026",
  "fy_2021_plan" : "11584121",
  "fy_2004_actual" : "4064405",
  "fy_2005_actual" : "4899386",
  "fy_2020_plan" : "10636591",
  "agn" : "098",
  "fy_2017_plan" : "6951124",
  "fy_2019_plan" : "9819317",
  "fy_2018_plan" : "8412368",
  "fy_2011_actual" : "4959691",
  "fy_2002_actual" : "3894252",
  "fy_2003_actual" : "4015170",
  "fy_2009_actual" : "5167466",
  "fy_2013_actual" : "4946494",
  "fy_2010_actual" : "4964091",
  "fy_2012_actual" : "5029320",
  "fy_2014_actual" : "9085208",
  "fy_2015_actual" : "8177672",
  "fy_2016_actual" : "7184901"
}
, {
  "fy_2006_actual" : "4021030",
  "fy_2007_actual" : "4276843",
  "agency_name" : "Debt Service",
  "fy_2008_actual" : "4689990",
  "fy_2021_plan" : "8086746",
  "fy_2004_actual" : "3620369",
  "fy_2005_actual" : "3946782",
  "fy_2020_plan" : "7610103",
  "agn" : "099",
  "fy_2017_plan" : "5840109",
  "fy_2019_plan" : "6967277",
  "fy_2018_plan" : "6264167",
  "fy_2011_actual" : "4763130",
  "fy_2002_actual" : "3314531",
  "fy_2003_actual" : "3007254",
  "fy_2009_actual" : "4615198",
  "fy_2013_actual" : "5395048",
  "fy_2010_actual" : "4930698",
  "fy_2012_actual" : "4975817",
  "fy_2014_actual" : "5356140",
  "fy_2015_actual" : "5707430",
  "fy_2016_actual" : "5641697"
}
, {
  "fy_2006_actual" : "10000",
  "fy_2007_actual" : "10000",
  "agency_name" : "M.A.C. Debt Service",
  "fy_2008_actual" : "2750",
  "fy_2021_plan" : "3620",
  "fy_2004_actual" : "501534",
  "fy_2005_actual" : "110772",
  "fy_2020_plan" : "3620",
  "agn" : "100",
  "fy_2017_plan" : "0",
  "fy_2019_plan" : "3620",
  "fy_2018_plan" : "0",
  "fy_2011_actual" : "0",
  "fy_2002_actual" : "462900",
  "fy_2003_actual" : "225236",
  "fy_2009_actual" : "0",
  "fy_2013_actual" : "0",
  "fy_2010_actual" : "0",
  "fy_2012_actual" : "0",
  "fy_2014_actual" : "0",
  "fy_2015_actual" : "0",
  "fy_2016_actual" : "0"
}
, {
  "fy_2006_actual" : "2903",
  "fy_2007_actual" : "3031",
  "agency_name" : "Public Advocate",
  "fy_2008_actual" : "3115",
  "fy_2021_plan" : "54200",
  "fy_2004_actual" : "2069",
  "fy_2005_actual" : "3110",
  "fy_2020_plan" : "54200",
  "agn" : "101",
  "fy_2017_plan" : "3599",
  "fy_2019_plan" : "54200",
  "fy_2018_plan" : "3620",
  "fy_2011_actual" : "2212",
  "fy_2002_actual" : "2821",
  "fy_2003_actual" : "1854",
  "fy_2009_actual" : "2809",
  "fy_2013_actual" : "2242",
  "fy_2010_actual" : "2573",
  "fy_2012_actual" : "2236",
  "fy_2014_actual" : "2322",
  "fy_2015_actual" : "2747",
  "fy_2016_actual" : "3289"
}
, {
  "fy_2006_actual" : "47886",
  "fy_2007_actual" : "50588",
  "agency_name" : "City Council",
  "fy_2008_actual" : "51211",
  "fy_2021_plan" : "5564",
  "fy_2004_actual" : "45461",
  "fy_2005_actual" : "46329",
  "fy_2020_plan" : "5564",
  "agn" : "102",
  "fy_2017_plan" : "64077",
  "fy_2019_plan" : "5564",
  "fy_2018_plan" : "64077",
  "fy_2011_actual" : "52111",
  "fy_2002_actual" : "47094",
  "fy_2003_actual" : "43876",
  "fy_2009_actual" : "49482",
  "fy_2013_actual" : "51591",
  "fy_2010_actual" : "51478",
  "fy_2012_actual" : "51900",
  "fy_2014_actual" : "51529",
  "fy_2015_actual" : "56911",
  "fy_2016_actual" : "59787"
}
, {
  "fy_2006_actual" : "3117",
  "fy_2007_actual" : "3630",
  "agency_name" : "City Clerk",
  "fy_2008_actual" : "3812",
  "fy_2021_plan" : "234765",
  "fy_2004_actual" : "2963",
  "fy_2005_actual" : "3009",
  "fy_2020_plan" : "233442",
  "agn" : "103",
  "fy_2017_plan" : "5909",
  "fy_2019_plan" : "226959",
  "fy_2018_plan" : "5714",
  "fy_2011_actual" : "4445",
  "fy_2002_actual" : "2650",
  "fy_2003_actual" : "2531",
  "fy_2009_actual" : "4330",
  "fy_2013_actual" : "4372",
  "fy_2010_actual" : "4221",
  "fy_2012_actual" : "4358",
  "fy_2014_actual" : "4753",
  "fy_2015_actual" : "5522",
  "fy_2016_actual" : "5490"
}
, {
  "fy_2006_actual" : "132764",
  "fy_2007_actual" : "133165",
  "agency_name" : "Department for the Aging",
  "fy_2008_actual" : "139140",
  "fy_2021_plan" : "142337",
  "fy_2004_actual" : "88119",
  "fy_2005_actual" : "99697",
  "fy_2020_plan" : "142337",
  "agn" : "125",
  "fy_2017_plan" : "215653",
  "fy_2019_plan" : "142337",
  "fy_2018_plan" : "250262",
  "fy_2011_actual" : "141246",
  "fy_2002_actual" : "166267",
  "fy_2003_actual" : "116533",
  "fy_2009_actual" : "166283",
  "fy_2013_actual" : "138276",
  "fy_2010_actual" : "158078",
  "fy_2012_actual" : "144643",
  "fy_2014_actual" : "152309",
  "fy_2015_actual" : "178473",
  "fy_2016_actual" : "186582"
}
, {
  "fy_2006_actual" : "134266",
  "fy_2007_actual" : "147812",
  "agency_name" : "Department of Cultural Affairs",
  "fy_2008_actual" : "159002",
  "fy_2021_plan" : "0",
  "fy_2004_actual" : "117152",
  "fy_2005_actual" : "120563",
  "fy_2020_plan" : "0",
  "agn" : "126",
  "fy_2017_plan" : "177578",
  "fy_2019_plan" : "0",
  "fy_2018_plan" : "188087",
  "fy_2011_actual" : "141448",
  "fy_2002_actual" : "122942",
  "fy_2003_actual" : "119435",
  "fy_2009_actual" : "148586",
  "fy_2013_actual" : "142423",
  "fy_2010_actual" : "140567",
  "fy_2012_actual" : "144648",
  "fy_2014_actual" : "149470",
  "fy_2015_actual" : "156953",
  "fy_2016_actual" : "156097"
}
, {
  "fy_2006_actual" : "37132",
  "fy_2007_actual" : "42585",
  "agency_name" : "Financial Info. Serv. Agency",
  "fy_2008_actual" : "43965",
  "fy_2021_plan" : "111581",
  "fy_2004_actual" : "29869",
  "fy_2005_actual" : "31100",
  "fy_2020_plan" : "111581",
  "agn" : "127",
  "fy_2017_plan" : "102706",
  "fy_2019_plan" : "110938",
  "fy_2018_plan" : "109319",
  "fy_2011_actual" : "47080",
  "fy_2002_actual" : "26105",
  "fy_2003_actual" : "26492",
  "fy_2009_actual" : "44666",
  "fy_2013_actual" : "78060",
  "fy_2010_actual" : "45885",
  "fy_2012_actual" : "75704",
  "fy_2014_actual" : "82426",
  "fy_2015_actual" : "83090",
  "fy_2016_actual" : "91390"
}
, {
  "fy_2006_actual" : "76493",
  "fy_2007_actual" : "85206",
  "agency_name" : "Department of Juvenile Justice",
  "fy_2008_actual" : "97632",
  "fy_2021_plan" : "0",
  "fy_2004_actual" : "62859",
  "fy_2005_actual" : "68299",
  "fy_2020_plan" : "0",
  "agn" : "130",
  "fy_2017_plan" : "0",
  "fy_2019_plan" : "0",
  "fy_2018_plan" : "0",
  "fy_2011_actual" : "165933",
  "fy_2002_actual" : "74565",
  "fy_2003_actual" : "76845",
  "fy_2009_actual" : "96496",
  "fy_2013_actual" : "0",
  "fy_2010_actual" : "103915",
  "fy_2012_actual" : "0",
  "fy_2014_actual" : "0",
  "fy_2015_actual" : "0",
  "fy_2016_actual" : "0"
}
, {
  "fy_2006_actual" : "8188",
  "fy_2007_actual" : "9426",
  "agency_name" : "Office of Payroll Admin.",
  "fy_2008_actual" : "11195",
  "fy_2021_plan" : "17008",
  "fy_2004_actual" : "6199",
  "fy_2005_actual" : "8205",
  "fy_2020_plan" : "17008",
  "agn" : "131",
  "fy_2017_plan" : "15781",
  "fy_2019_plan" : "17008",
  "fy_2018_plan" : "16316",
  "fy_2011_actual" : "56968",
  "fy_2002_actual" : "5900",
  "fy_2003_actual" : "5812",
  "fy_2009_actual" : "11632",
  "fy_2013_actual" : "12229",
  "fy_2010_actual" : "22171",
  "fy_2012_actual" : "13392",
  "fy_2014_actual" : "12713",
  "fy_2015_actual" : "13769",
  "fy_2016_actual" : "14762"
}
, {
  "fy_2006_actual" : "2658",
  "fy_2007_actual" : "2845",
  "agency_name" : "Independent Budget Office",
  "fy_2008_actual" : "2925",
  "fy_2021_plan" : "5133",
  "fy_2004_actual" : "2422",
  "fy_2005_actual" : "2518",
  "fy_2020_plan" : "5398",
  "agn" : "132",
  "fy_2017_plan" : "5420",
  "fy_2019_plan" : "5399",
  "fy_2018_plan" : "5548",
  "fy_2011_actual" : "3397",
  "fy_2002_actual" : "2551",
  "fy_2003_actual" : "2262",
  "fy_2009_actual" : "2884",
  "fy_2013_actual" : "3889",
  "fy_2010_actual" : "3189",
  "fy_2012_actual" : "3693",
  "fy_2014_actual" : "3998",
  "fy_2015_actual" : "3944",
  "fy_2016_actual" : "3991"
}
, {
  "fy_2006_actual" : "729",
  "fy_2007_actual" : "785",
  "agency_name" : "Equal Employment Practices Com",
  "fy_2008_actual" : "764",
  "fy_2021_plan" : "1187",
  "fy_2004_actual" : "474",
  "fy_2005_actual" : "538",
  "fy_2020_plan" : "1187",
  "agn" : "133",
  "fy_2017_plan" : "1139",
  "fy_2019_plan" : "1187",
  "fy_2018_plan" : "1108",
  "fy_2011_actual" : "726",
  "fy_2002_actual" : "342",
  "fy_2003_actual" : "475",
  "fy_2009_actual" : "766",
  "fy_2013_actual" : "421",
  "fy_2010_actual" : "751",
  "fy_2012_actual" : "627",
  "fy_2014_actual" : "464",
  "fy_2015_actual" : "701",
  "fy_2016_actual" : "764"
}
, {
  "fy_2006_actual" : "465",
  "fy_2007_actual" : "530",
  "agency_name" : "Civil Service Commission",
  "fy_2008_actual" : "583",
  "fy_2021_plan" : "1092",
  "fy_2004_actual" : "461",
  "fy_2005_actual" : "483",
  "fy_2020_plan" : "1092",
  "agn" : "134",
  "fy_2017_plan" : "1086",
  "fy_2019_plan" : "1092",
  "fy_2018_plan" : "1094",
  "fy_2011_actual" : "491",
  "fy_2002_actual" : "471",
  "fy_2003_actual" : "480",
  "fy_2009_actual" : "607",
  "fy_2013_actual" : "767",
  "fy_2010_actual" : "554",
  "fy_2012_actual" : "651",
  "fy_2014_actual" : "799",
  "fy_2015_actual" : "735",
  "fy_2016_actual" : "781"
}
, {
  "fy_2006_actual" : "2945",
  "fy_2007_actual" : "3550",
  "agency_name" : "Landmarks Preservation Comm.",
  "fy_2008_actual" : "3727",
  "fy_2021_plan" : "5691",
  "fy_2004_actual" : "2539",
  "fy_2005_actual" : "2877",
  "fy_2020_plan" : "5671",
  "agn" : "136",
  "fy_2017_plan" : "5173",
  "fy_2019_plan" : "5680",
  "fy_2018_plan" : "5692",
  "fy_2011_actual" : "3989",
  "fy_2002_actual" : "2651",
  "fy_2003_actual" : "2450",
  "fy_2009_actual" : "3858",
  "fy_2013_actual" : "3893",
  "fy_2010_actual" : "4090",
  "fy_2012_actual" : "3720",
  "fy_2014_actual" : "4221",
  "fy_2015_actual" : "4326",
  "fy_2016_actual" : "4780"
}
, {
  "fy_2006_actual" : "0",
  "fy_2007_actual" : "0",
  "agency_name" : "Districting Commission",
  "fy_2008_actual" : "0",
  "fy_2021_plan" : "0",
  "fy_2004_actual" : "4",
  "fy_2005_actual" : "0",
  "fy_2020_plan" : "0",
  "agn" : "138",
  "fy_2017_plan" : "0",
  "fy_2019_plan" : "0",
  "fy_2018_plan" : "0",
  "fy_2011_actual" : "0",
  "fy_2002_actual" : "0",
  "fy_2003_actual" : "1660",
  "fy_2009_actual" : "0",
  "fy_2013_actual" : "1381",
  "fy_2010_actual" : "0",
  "fy_2012_actual" : "0",
  "fy_2014_actual" : "14",
  "fy_2015_actual" : "0",
  "fy_2016_actual" : "0"
}
, {
  "fy_2006_actual" : "25554",
  "fy_2007_actual" : "25953",
  "agency_name" : "Taxi & Limousine Commission",
  "fy_2008_actual" : "27763",
  "fy_2021_plan" : "59292",
  "fy_2004_actual" : "23165",
  "fy_2005_actual" : "24847",
  "fy_2020_plan" : "59120",
  "agn" : "156",
  "fy_2017_plan" : "46890",
  "fy_2019_plan" : "60768",
  "fy_2018_plan" : "57479",
  "fy_2011_actual" : "30171",
  "fy_2002_actual" : "22597",
  "fy_2003_actual" : "21527",
  "fy_2009_actual" : "28875",
  "fy_2013_actual" : "36527",
  "fy_2010_actual" : "30098",
  "fy_2012_actual" : "31716",
  "fy_2014_actual" : "46394",
  "fy_2015_actual" : "52446",
  "fy_2016_actual" : "47931"
}
, {
  "fy_2006_actual" : "2457",
  "fy_2007_actual" : "2683",
  "agency_name" : "Commission on Human Rights",
  "fy_2008_actual" : "2506",
  "fy_2021_plan" : "14137",
  "fy_2004_actual" : "2828",
  "fy_2005_actual" : "2590",
  "fy_2020_plan" : "14137",
  "agn" : "226",
  "fy_2017_plan" : "11477",
  "fy_2019_plan" : "14137",
  "fy_2018_plan" : "14759",
  "fy_2011_actual" : "1916",
  "fy_2002_actual" : "3192",
  "fy_2003_actual" : "3222",
  "fy_2009_actual" : "2496",
  "fy_2013_actual" : "2125",
  "fy_2010_actual" : "2308",
  "fy_2012_actual" : "2054",
  "fy_2014_actual" : "1682",
  "fy_2015_actual" : "1558",
  "fy_2016_actual" : "8595"
}
, {
  "fy_2006_actual" : "180391",
  "fy_2007_actual" : "210724",
  "agency_name" : "Youth & Community Development",
  "fy_2008_actual" : "259368",
  "fy_2021_plan" : "476291",
  "fy_2004_actual" : "115124",
  "fy_2005_actual" : "126952",
  "fy_2020_plan" : "473063",
  "agn" : "260",
  "fy_2017_plan" : "482219",
  "fy_2019_plan" : "455255",
  "fy_2018_plan" : "586717",
  "fy_2011_actual" : "223489",
  "fy_2002_actual" : "93681",
  "fy_2003_actual" : "89980",
  "fy_2009_actual" : "254942",
  "fy_2013_actual" : "241438",
  "fy_2010_actual" : "220245",
  "fy_2012_actual" : "213642",
  "fy_2014_actual" : "296762",
  "fy_2015_actual" : "345319",
  "fy_2016_actual" : "420795"
}
, {
  "fy_2006_actual" : "1435",
  "fy_2007_actual" : "1741",
  "agency_name" : "Conflicts of Interest Board",
  "fy_2008_actual" : "1882",
  "fy_2021_plan" : "2581",
  "fy_2004_actual" : "1438",
  "fy_2005_actual" : "1423",
  "fy_2020_plan" : "2581",
  "agn" : "312",
  "fy_2017_plan" : "2561",
  "fy_2019_plan" : "2581",
  "fy_2018_plan" : "2580",
  "fy_2011_actual" : "1981",
  "fy_2002_actual" : "1624",
  "fy_2003_actual" : "1547",
  "fy_2009_actual" : "1898",
  "fy_2013_actual" : "2032",
  "fy_2010_actual" : "1909",
  "fy_2012_actual" : "1960",
  "fy_2014_actual" : "2054",
  "fy_2015_actual" : "2193",
  "fy_2016_actual" : "2380"
}
, {
  "fy_2006_actual" : "1534",
  "fy_2007_actual" : "1634",
  "agency_name" : "Office of Collective Barg.",
  "fy_2008_actual" : "1671",
  "fy_2021_plan" : "2166",
  "fy_2004_actual" : "1411",
  "fy_2005_actual" : "1456",
  "fy_2020_plan" : "2166",
  "agn" : "313",
  "fy_2017_plan" : "2128",
  "fy_2019_plan" : "2166",
  "fy_2018_plan" : "2300",
  "fy_2011_actual" : "1807",
  "fy_2002_actual" : "1330",
  "fy_2003_actual" : "1378",
  "fy_2009_actual" : "1690",
  "fy_2013_actual" : "1893",
  "fy_2010_actual" : "1831",
  "fy_2012_actual" : "1868",
  "fy_2014_actual" : "1900",
  "fy_2015_actual" : "1510",
  "fy_2016_actual" : "2006"
}
, {
  "fy_2006_actual" : "13007",
  "fy_2007_actual" : "13131",
  "agency_name" : "Community Boards (All)",
  "fy_2008_actual" : "13601",
  "fy_2021_plan" : "17406",
  "fy_2004_actual" : "11940",
  "fy_2005_actual" : "12285",
  "fy_2020_plan" : "17406",
  "agn" : "499",
  "fy_2017_plan" : "17822",
  "fy_2019_plan" : "17406",
  "fy_2018_plan" : "17581",
  "fy_2011_actual" : "14020",
  "fy_2002_actual" : "11407",
  "fy_2003_actual" : "11531",
  "fy_2009_actual" : "13882",
  "fy_2013_actual" : "14387",
  "fy_2010_actual" : "13931",
  "fy_2012_actual" : "14315",
  "fy_2014_actual" : "14507",
  "fy_2015_actual" : "15093",
  "fy_2016_actual" : "15759"
}
, {
  "fy_2006_actual" : "60637",
  "fy_2007_actual" : "62434",
  "agency_name" : "Department of Probation",
  "fy_2008_actual" : "64131",
  "fy_2021_plan" : "80806",
  "fy_2004_actual" : "56678",
  "fy_2005_actual" : "60587",
  "fy_2020_plan" : "80735",
  "agn" : "781",
  "fy_2017_plan" : "74432",
  "fy_2019_plan" : "80899",
  "fy_2018_plan" : "81933",
  "fy_2011_actual" : "61393",
  "fy_2002_actual" : "59297",
  "fy_2003_actual" : "54502",
  "fy_2009_actual" : "62980",
  "fy_2013_actual" : "58684",
  "fy_2010_actual" : "62683",
  "fy_2012_actual" : "59492",
  "fy_2014_actual" : "59453",
  "fy_2015_actual" : "65294",
  "fy_2016_actual" : "64404"
}
, {
  "fy_2006_actual" : "38369",
  "fy_2007_actual" : "55308",
  "agency_name" : "Dept. Small Business Services",
  "fy_2008_actual" : "75386",
  "fy_2021_plan" : "83783",
  "fy_2004_actual" : "36454",
  "fy_2005_actual" : "31075",
  "fy_2020_plan" : "89013",
  "agn" : "801",
  "fy_2017_plan" : "150328",
  "fy_2019_plan" : "94477",
  "fy_2018_plan" : "143291",
  "fy_2011_actual" : "60588",
  "fy_2002_actual" : "88086",
  "fy_2003_actual" : "18958",
  "fy_2009_actual" : "75404",
  "fy_2013_actual" : "47081",
  "fy_2010_actual" : "53278",
  "fy_2012_actual" : "73018",
  "fy_2014_actual" : "65592",
  "fy_2015_actual" : "85491",
  "fy_2016_actual" : "131179"
}
, {
  "fy_2006_actual" : "68516",
  "fy_2007_actual" : "74217",
  "agency_name" : "Housing Preservation & Dev.",
  "fy_2008_actual" : "75273",
  "fy_2021_plan" : "80955",
  "fy_2004_actual" : "56286",
  "fy_2005_actual" : "53362",
  "fy_2020_plan" : "89340",
  "agn" : "806",
  "fy_2017_plan" : "182452",
  "fy_2019_plan" : "89172",
  "fy_2018_plan" : "143817",
  "fy_2011_actual" : "59108",
  "fy_2002_actual" : "63211",
  "fy_2003_actual" : "57098",
  "fy_2009_actual" : "74461",
  "fy_2013_actual" : "45884",
  "fy_2010_actual" : "68171",
  "fy_2012_actual" : "35819",
  "fy_2014_actual" : "58802",
  "fy_2015_actual" : "70622",
  "fy_2016_actual" : "83502"
}
, {
  "fy_2006_actual" : "81467",
  "fy_2007_actual" : "87086",
  "agency_name" : "Department of Buildings",
  "fy_2008_actual" : "99387",
  "fy_2021_plan" : "158591",
  "fy_2004_actual" : "57770",
  "fy_2005_actual" : "64240",
  "fy_2020_plan" : "165671",
  "agn" : "810",
  "fy_2017_plan" : "156196",
  "fy_2019_plan" : "164401",
  "fy_2018_plan" : "183717",
  "fy_2011_actual" : "98474",
  "fy_2002_actual" : "55750",
  "fy_2003_actual" : "57445",
  "fy_2009_actual" : "109677",
  "fy_2013_actual" : "97893",
  "fy_2010_actual" : "101530",
  "fy_2012_actual" : "95062",
  "fy_2014_actual" : "98489",
  "fy_2015_actual" : "108498",
  "fy_2016_actual" : "134725"
}
, {
  "fy_2006_actual" : "587106",
  "fy_2007_actual" : "589107",
  "agency_name" : "Dept Health & Mental Hygiene",
  "fy_2008_actual" : "570456",
  "fy_2021_plan" : "829398",
  "fy_2004_actual" : "555913",
  "fy_2005_actual" : "539751",
  "fy_2020_plan" : "811603",
  "agn" : "816",
  "fy_2017_plan" : "644621",
  "fy_2019_plan" : "778590",
  "fy_2018_plan" : "758226",
  "fy_2011_actual" : "606402",
  "fy_2002_actual" : "448564",
  "fy_2003_actual" : "518987",
  "fy_2009_actual" : "656111",
  "fy_2013_actual" : "616438",
  "fy_2010_actual" : "641651",
  "fy_2012_actual" : "612631",
  "fy_2014_actual" : "641549",
  "fy_2015_actual" : "781595",
  "fy_2016_actual" : "579516"
}
, {
  "fy_2006_actual" : "0",
  "fy_2007_actual" : "0",
  "agency_name" : "Dept of Mental Health",
  "fy_2008_actual" : "0",
  "fy_2021_plan" : "0",
  "fy_2004_actual" : "0",
  "fy_2005_actual" : "0",
  "fy_2020_plan" : "0",
  "agn" : "817",
  "fy_2017_plan" : "0",
  "fy_2019_plan" : "0",
  "fy_2018_plan" : "0",
  "fy_2011_actual" : "0",
  "fy_2002_actual" : "84754",
  "fy_2003_actual" : "0",
  "fy_2009_actual" : "0",
  "fy_2013_actual" : "0",
  "fy_2010_actual" : "0",
  "fy_2012_actual" : "0",
  "fy_2014_actual" : "0",
  "fy_2015_actual" : "0",
  "fy_2016_actual" : "0"
}
, {
  "fy_2006_actual" : "1469669",
  "fy_2007_actual" : "663259",
  "agency_name" : "Health + Hospitals",
  "fy_2008_actual" : "128181",
  "fy_2021_plan" : "806167",
  "fy_2004_actual" : "818027",
  "fy_2005_actual" : "997358",
  "fy_2020_plan" : "906782",
  "agn" : "819",
  "fy_2017_plan" : "696872",
  "fy_2019_plan" : "804664",
  "fy_2018_plan" : "785549",
  "fy_2011_actual" : "83598",
  "fy_2002_actual" : "826437",
  "fy_2003_actual" : "826572",
  "fy_2009_actual" : "94267",
  "fy_2013_actual" : "70765",
  "fy_2010_actual" : "88756",
  "fy_2012_actual" : "75477",
  "fy_2014_actual" : "129268",
  "fy_2015_actual" : "214930",
  "fy_2016_actual" : "788248"
}
, {
  "fy_2006_actual" : "0",
  "fy_2007_actual" : "0",
  "agency_name" : "Office of Administrative Trials and Hearings",
  "fy_2008_actual" : "0",
  "fy_2021_plan" : "49944",
  "fy_2004_actual" : "0",
  "fy_2005_actual" : "0",
  "fy_2020_plan" : "49944",
  "agn" : "820",
  "fy_2017_plan" : "41379",
  "fy_2019_plan" : "49944",
  "fy_2018_plan" : "48879",
  "fy_2011_actual" : "23322",
  "fy_2002_actual" : "0",
  "fy_2003_actual" : "0",
  "fy_2009_actual" : "0",
  "fy_2013_actual" : "30693",
  "fy_2010_actual" : "0",
  "fy_2012_actual" : "30465",
  "fy_2014_actual" : "31346",
  "fy_2015_actual" : "34371",
  "fy_2016_actual" : "36344"
}
, {
  "fy_2006_actual" : "757796",
  "fy_2007_actual" : "808320",
  "agency_name" : "Dept of Environmental Prot.",
  "fy_2008_actual" : "849897",
  "fy_2021_plan" : "1140106",
  "fy_2004_actual" : "661120",
  "fy_2005_actual" : "704929",
  "fy_2020_plan" : "1154372",
  "agn" : "826",
  "fy_2017_plan" : "1166158",
  "fy_2019_plan" : "1168910",
  "fy_2018_plan" : "1187275",
  "fy_2011_actual" : "924669",
  "fy_2002_actual" : "626224",
  "fy_2003_actual" : "655668",
  "fy_2009_actual" : "907759",
  "fy_2013_actual" : "977379",
  "fy_2010_actual" : "1138928",
  "fy_2012_actual" : "942522",
  "fy_2014_actual" : "1018639",
  "fy_2015_actual" : "1014353",
  "fy_2016_actual" : "1039951"
}
, {
  "fy_2006_actual" : "1049104",
  "fy_2007_actual" : "1144784",
  "agency_name" : "Department of Sanitation",
  "fy_2008_actual" : "1206386",
  "fy_2021_plan" : "1701745",
  "fy_2004_actual" : "965605",
  "fy_2005_actual" : "1009084",
  "fy_2020_plan" : "1704120",
  "agn" : "827",
  "fy_2017_plan" : "1569762",
  "fy_2019_plan" : "1690450",
  "fy_2018_plan" : "1661959",
  "fy_2011_actual" : "1370065",
  "fy_2002_actual" : "909920",
  "fy_2003_actual" : "956840",
  "fy_2009_actual" : "1221933",
  "fy_2013_actual" : "1242560",
  "fy_2010_actual" : "1267964",
  "fy_2012_actual" : "1241535",
  "fy_2014_actual" : "1385890",
  "fy_2015_actual" : "1448991",
  "fy_2016_actual" : "1474974"
}
, {
  "fy_2006_actual" : "4957",
  "fy_2007_actual" : "5135",
  "agency_name" : "Business Integrity Commission",
  "fy_2008_actual" : "5771",
  "fy_2021_plan" : "8611",
  "fy_2004_actual" : "4378",
  "fy_2005_actual" : "4816",
  "fy_2020_plan" : "8611",
  "agn" : "829",
  "fy_2017_plan" : "9703",
  "fy_2019_plan" : "8611",
  "fy_2018_plan" : "8734",
  "fy_2011_actual" : "6843",
  "fy_2002_actual" : "2627",
  "fy_2003_actual" : "4680",
  "fy_2009_actual" : "6264",
  "fy_2013_actual" : "6769",
  "fy_2010_actual" : "6914",
  "fy_2012_actual" : "6743",
  "fy_2014_actual" : "6788",
  "fy_2015_actual" : "7077",
  "fy_2016_actual" : "7344"
}
, {
  "fy_2006_actual" : "196201",
  "fy_2007_actual" : "200698",
  "agency_name" : "Department of Finance",
  "fy_2008_actual" : "210240",
  "fy_2021_plan" : "293823",
  "fy_2004_actual" : "201277",
  "fy_2005_actual" : "197565",
  "fy_2020_plan" : "293781",
  "agn" : "836",
  "fy_2017_plan" : "272189",
  "fy_2019_plan" : "293553",
  "fy_2018_plan" : "297284",
  "fy_2011_actual" : "214418",
  "fy_2002_actual" : "179816",
  "fy_2003_actual" : "176556",
  "fy_2009_actual" : "218656",
  "fy_2013_actual" : "217216",
  "fy_2010_actual" : "224716",
  "fy_2012_actual" : "216702",
  "fy_2014_actual" : "235703",
  "fy_2015_actual" : "247079",
  "fy_2016_actual" : "253757"
}
, {
  "fy_2006_actual" : "337331",
  "fy_2007_actual" : "358108",
  "agency_name" : "Department of Transportation",
  "fy_2008_actual" : "421804",
  "fy_2021_plan" : "576311",
  "fy_2004_actual" : "280376",
  "fy_2005_actual" : "300156",
  "fy_2020_plan" : "574231",
  "agn" : "841",
  "fy_2017_plan" : "560233",
  "fy_2019_plan" : "563586",
  "fy_2018_plan" : "559956",
  "fy_2011_actual" : "421005",
  "fy_2002_actual" : "271260",
  "fy_2003_actual" : "255506",
  "fy_2009_actual" : "457419",
  "fy_2013_actual" : "413531",
  "fy_2010_actual" : "434353",
  "fy_2012_actual" : "415585",
  "fy_2014_actual" : "453685",
  "fy_2015_actual" : "516157",
  "fy_2016_actual" : "541026"
}
, {
  "fy_2006_actual" : "221867",
  "fy_2007_actual" : "250150",
  "agency_name" : "Dept of Parks and Recreation",
  "fy_2008_actual" : "277209",
  "fy_2021_plan" : "382370",
  "fy_2004_actual" : "184255",
  "fy_2005_actual" : "202613",
  "fy_2020_plan" : "383631",
  "agn" : "846",
  "fy_2017_plan" : "409016",
  "fy_2019_plan" : "385135",
  "fy_2018_plan" : "417085",
  "fy_2011_actual" : "267588",
  "fy_2002_actual" : "167554",
  "fy_2003_actual" : "159653",
  "fy_2009_actual" : "279250",
  "fy_2013_actual" : "262857",
  "fy_2010_actual" : "273753",
  "fy_2012_actual" : "257066",
  "fy_2014_actual" : "300589",
  "fy_2015_actual" : "332280",
  "fy_2016_actual" : "355286"
}
, {
  "fy_2006_actual" : "3235",
  "fy_2007_actual" : "4671",
  "agency_name" : "Dept. of Design & Construction",
  "fy_2008_actual" : "7579",
  "fy_2021_plan" : "14437",
  "fy_2004_actual" : "0",
  "fy_2005_actual" : "0",
  "fy_2020_plan" : "14437",
  "agn" : "850",
  "fy_2017_plan" : "12703",
  "fy_2019_plan" : "14410",
  "fy_2018_plan" : "16723",
  "fy_2011_actual" : "1128",
  "fy_2002_actual" : "27269",
  "fy_2003_actual" : "6437",
  "fy_2009_actual" : "9360",
  "fy_2013_actual" : "8545",
  "fy_2010_actual" : "3671",
  "fy_2012_actual" : "1268",
  "fy_2014_actual" : "2144",
  "fy_2015_actual" : "4448",
  "fy_2016_actual" : "4622"
}
, {
  "fy_2006_actual" : "153615",
  "fy_2007_actual" : "179008",
  "agency_name" : "Dept of Citywide Admin Srvces",
  "fy_2008_actual" : "195882",
  "fy_2021_plan" : "275956",
  "fy_2004_actual" : "136922",
  "fy_2005_actual" : "150719",
  "fy_2020_plan" : "274866",
  "agn" : "856",
  "fy_2017_plan" : "312576",
  "fy_2019_plan" : "274190",
  "fy_2018_plan" : "325004",
  "fy_2011_actual" : "210887",
  "fy_2002_actual" : "162231",
  "fy_2003_actual" : "143601",
  "fy_2009_actual" : "216716",
  "fy_2013_actual" : "201079",
  "fy_2010_actual" : "218360",
  "fy_2012_actual" : "199548",
  "fy_2014_actual" : "220700",
  "fy_2015_actual" : "327180",
  "fy_2016_actual" : "281909"
}
, {
  "fy_2006_actual" : "107867",
  "fy_2007_actual" : "132641",
  "agency_name" : "D.O.I.T.T.",
  "fy_2008_actual" : "179365",
  "fy_2021_plan" : "438831",
  "fy_2004_actual" : "82439",
  "fy_2005_actual" : "101330",
  "fy_2020_plan" : "439233",
  "agn" : "858",
  "fy_2017_plan" : "449676",
  "fy_2019_plan" : "443596",
  "fy_2018_plan" : "466574",
  "fy_2011_actual" : "261626",
  "fy_2002_actual" : "53506",
  "fy_2003_actual" : "70636",
  "fy_2009_actual" : "220647",
  "fy_2013_actual" : "259150",
  "fy_2010_actual" : "219914",
  "fy_2012_actual" : "264529",
  "fy_2014_actual" : "307286",
  "fy_2015_actual" : "334977",
  "fy_2016_actual" : "401704"
}
, {
  "fy_2006_actual" : "3886",
  "fy_2007_actual" : "4078",
  "agency_name" : "Dept of Records & Info Serv.",
  "fy_2008_actual" : "5178",
  "fy_2021_plan" : "8417",
  "fy_2004_actual" : "3698",
  "fy_2005_actual" : "3678",
  "fy_2020_plan" : "8417",
  "agn" : "860",
  "fy_2017_plan" : "7202",
  "fy_2019_plan" : "8417",
  "fy_2018_plan" : "7733",
  "fy_2011_actual" : "4802",
  "fy_2002_actual" : "3303",
  "fy_2003_actual" : "3386",
  "fy_2009_actual" : "5278",
  "fy_2013_actual" : "4667",
  "fy_2010_actual" : "4740",
  "fy_2012_actual" : "4278",
  "fy_2014_actual" : "4937",
  "fy_2015_actual" : "5638",
  "fy_2016_actual" : "7236"
}
, {
  "fy_2006_actual" : "12781",
  "fy_2007_actual" : "15398",
  "agency_name" : "Department of Consumer Affairs",
  "fy_2008_actual" : "17052",
  "fy_2021_plan" : "37076",
  "fy_2004_actual" : "11799",
  "fy_2005_actual" : "12934",
  "fy_2020_plan" : "37076",
  "agn" : "866",
  "fy_2017_plan" : "33712",
  "fy_2019_plan" : "37076",
  "fy_2018_plan" : "37618",
  "fy_2011_actual" : "17053",
  "fy_2002_actual" : "12258",
  "fy_2003_actual" : "12153",
  "fy_2009_actual" : "18506",
  "fy_2013_actual" : "23004",
  "fy_2010_actual" : "17425",
  "fy_2012_actual" : "21104",
  "fy_2014_actual" : "27852",
  "fy_2015_actual" : "32642",
  "fy_2016_actual" : "31897"
}
, {
  "fy_2006_actual" : "68466",
  "fy_2007_actual" : "71183",
  "agency_name" : "District Attorney - N.Y.",
  "fy_2008_actual" : "74669",
  "fy_2021_plan" : "99886",
  "fy_2004_actual" : "66875",
  "fy_2005_actual" : "64975",
  "fy_2020_plan" : "99886",
  "agn" : "901",
  "fy_2017_plan" : "99175",
  "fy_2019_plan" : "99875",
  "fy_2018_plan" : "99541",
  "fy_2011_actual" : "77508",
  "fy_2002_actual" : "67086",
  "fy_2003_actual" : "63777",
  "fy_2009_actual" : "74574",
  "fy_2013_actual" : "85500",
  "fy_2010_actual" : "82882",
  "fy_2012_actual" : "79331",
  "fy_2014_actual" : "82928",
  "fy_2015_actual" : "94628",
  "fy_2016_actual" : "95063"
}
, {
  "fy_2006_actual" : "38857",
  "fy_2007_actual" : "41163",
  "agency_name" : "District Attorney - Bronx",
  "fy_2008_actual" : "43715",
  "fy_2021_plan" : "69350",
  "fy_2004_actual" : "36602",
  "fy_2005_actual" : "37902",
  "fy_2020_plan" : "69350",
  "agn" : "902",
  "fy_2017_plan" : "68625",
  "fy_2019_plan" : "69352",
  "fy_2018_plan" : "69291",
  "fy_2011_actual" : "44604",
  "fy_2002_actual" : "38992",
  "fy_2003_actual" : "35897",
  "fy_2009_actual" : "43263",
  "fy_2013_actual" : "45732",
  "fy_2010_actual" : "45749",
  "fy_2012_actual" : "43767",
  "fy_2014_actual" : "49060",
  "fy_2015_actual" : "54000",
  "fy_2016_actual" : "54989"
}
, {
  "fy_2006_actual" : "67447",
  "fy_2007_actual" : "70429",
  "agency_name" : "District Attorney - Kings",
  "fy_2008_actual" : "73589",
  "fy_2021_plan" : "94313",
  "fy_2004_actual" : "61268",
  "fy_2005_actual" : "66247",
  "fy_2020_plan" : "94313",
  "agn" : "903",
  "fy_2017_plan" : "93738",
  "fy_2019_plan" : "94323",
  "fy_2018_plan" : "94906",
  "fy_2011_actual" : "76253",
  "fy_2002_actual" : "71802",
  "fy_2003_actual" : "61516",
  "fy_2009_actual" : "73393",
  "fy_2013_actual" : "78166",
  "fy_2010_actual" : "78033",
  "fy_2012_actual" : "73329",
  "fy_2014_actual" : "81324",
  "fy_2015_actual" : "87590",
  "fy_2016_actual" : "90040"
}
, {
  "fy_2006_actual" : "35567",
  "fy_2007_actual" : "37909",
  "agency_name" : "District Attorney - Queens",
  "fy_2008_actual" : "40364",
  "fy_2021_plan" : "62595",
  "fy_2004_actual" : "34698",
  "fy_2005_actual" : "34351",
  "fy_2020_plan" : "62595",
  "agn" : "904",
  "fy_2017_plan" : "62408",
  "fy_2019_plan" : "62587",
  "fy_2018_plan" : "62353",
  "fy_2011_actual" : "42367",
  "fy_2002_actual" : "35201",
  "fy_2003_actual" : "32592",
  "fy_2009_actual" : "40715",
  "fy_2013_actual" : "44274",
  "fy_2010_actual" : "43733",
  "fy_2012_actual" : "42670",
  "fy_2014_actual" : "46932",
  "fy_2015_actual" : "51126",
  "fy_2016_actual" : "53906"
}
, {
  "fy_2006_actual" : "5958",
  "fy_2007_actual" : "6591",
  "agency_name" : "District Attorney - Richmond",
  "fy_2008_actual" : "7231",
  "fy_2021_plan" : "13866",
  "fy_2004_actual" : "5765",
  "fy_2005_actual" : "5902",
  "fy_2020_plan" : "13866",
  "agn" : "905",
  "fy_2017_plan" : "13777",
  "fy_2019_plan" : "13865",
  "fy_2018_plan" : "14161",
  "fy_2011_actual" : "7517",
  "fy_2002_actual" : "6045",
  "fy_2003_actual" : "5430",
  "fy_2009_actual" : "7235",
  "fy_2013_actual" : "8027",
  "fy_2010_actual" : "7671",
  "fy_2012_actual" : "7591",
  "fy_2014_actual" : "8431",
  "fy_2015_actual" : "9375",
  "fy_2016_actual" : "9999"
}
, {
  "fy_2006_actual" : "14141",
  "fy_2007_actual" : "15066",
  "agency_name" : "Off. of Prosec. & Spec. Narc.",
  "fy_2008_actual" : "16105",
  "fy_2021_plan" : "21370",
  "fy_2004_actual" : "13490",
  "fy_2005_actual" : "13511",
  "fy_2020_plan" : "21370",
  "agn" : "906",
  "fy_2017_plan" : "21007",
  "fy_2019_plan" : "21365",
  "fy_2018_plan" : "21265",
  "fy_2011_actual" : "15977",
  "fy_2002_actual" : "13986",
  "fy_2003_actual" : "12920",
  "fy_2009_actual" : "15725",
  "fy_2013_actual" : "16218",
  "fy_2010_actual" : "16904",
  "fy_2012_actual" : "15827",
  "fy_2014_actual" : "16688",
  "fy_2015_actual" : "18002",
  "fy_2016_actual" : "20500"
}
, {
  "fy_2006_actual" : "1086",
  "fy_2007_actual" : "1104",
  "agency_name" : "Public Administrator - N.Y.",
  "fy_2008_actual" : "1143",
  "fy_2021_plan" : "2818",
  "fy_2004_actual" : "964",
  "fy_2005_actual" : "1030",
  "fy_2020_plan" : "2818",
  "agn" : "941",
  "fy_2017_plan" : "1729",
  "fy_2019_plan" : "2818",
  "fy_2018_plan" : "2863",
  "fy_2011_actual" : "1126",
  "fy_2002_actual" : "915",
  "fy_2003_actual" : "992",
  "fy_2009_actual" : "1148",
  "fy_2013_actual" : "1335",
  "fy_2010_actual" : "1168",
  "fy_2012_actual" : "1184",
  "fy_2014_actual" : "1397",
  "fy_2015_actual" : "1504",
  "fy_2016_actual" : "1600"
}
, {
  "fy_2006_actual" : "317",
  "fy_2007_actual" : "429",
  "agency_name" : "Public Administrator - Bronx",
  "fy_2008_actual" : "418",
  "fy_2021_plan" : "704",
  "fy_2004_actual" : "320",
  "fy_2005_actual" : "308",
  "fy_2020_plan" : "704",
  "agn" : "942",
  "fy_2017_plan" : "695",
  "fy_2019_plan" : "704",
  "fy_2018_plan" : "724",
  "fy_2011_actual" : "388",
  "fy_2002_actual" : "329",
  "fy_2003_actual" : "331",
  "fy_2009_actual" : "508",
  "fy_2013_actual" : "538",
  "fy_2010_actual" : "426",
  "fy_2012_actual" : "481",
  "fy_2014_actual" : "532",
  "fy_2015_actual" : "603",
  "fy_2016_actual" : "616"
}
, {
  "fy_2006_actual" : "454",
  "fy_2007_actual" : "501",
  "agency_name" : "Public Administrator- Brooklyn",
  "fy_2008_actual" : "536",
  "fy_2021_plan" : "856",
  "fy_2004_actual" : "403",
  "fy_2005_actual" : "356",
  "fy_2020_plan" : "856",
  "agn" : "943",
  "fy_2017_plan" : "852",
  "fy_2019_plan" : "856",
  "fy_2018_plan" : "852",
  "fy_2011_actual" : "553",
  "fy_2002_actual" : "439",
  "fy_2003_actual" : "419",
  "fy_2009_actual" : "493",
  "fy_2013_actual" : "531",
  "fy_2010_actual" : "549",
  "fy_2012_actual" : "472",
  "fy_2014_actual" : "604",
  "fy_2015_actual" : "641",
  "fy_2016_actual" : "686"
}
, {
  "fy_2006_actual" : "414",
  "fy_2007_actual" : "408",
  "agency_name" : "Public Administrator - Queens",
  "fy_2008_actual" : "421",
  "fy_2021_plan" : "633",
  "fy_2004_actual" : "344",
  "fy_2005_actual" : "350",
  "fy_2020_plan" : "633",
  "agn" : "944",
  "fy_2017_plan" : "613",
  "fy_2019_plan" : "633",
  "fy_2018_plan" : "621",
  "fy_2011_actual" : "425",
  "fy_2002_actual" : "343",
  "fy_2003_actual" : "344",
  "fy_2009_actual" : "436",
  "fy_2013_actual" : "449",
  "fy_2010_actual" : "424",
  "fy_2012_actual" : "421",
  "fy_2014_actual" : "471",
  "fy_2015_actual" : "484",
  "fy_2016_actual" : "503"
}
, {
  "fy_2006_actual" : "339",
  "fy_2007_actual" : "348",
  "agency_name" : "Public Administrator -Richmond",
  "fy_2008_actual" : "362",
  "fy_2021_plan" : "531",
  "fy_2004_actual" : "234",
  "fy_2005_actual" : "269",
  "fy_2020_plan" : "531",
  "agn" : "945",
  "fy_2017_plan" : "518",
  "fy_2019_plan" : "531",
  "fy_2018_plan" : "525",
  "fy_2011_actual" : "375",
  "fy_2002_actual" : "237",
  "fy_2003_actual" : "223",
  "fy_2009_actual" : "365",
  "fy_2013_actual" : "441",
  "fy_2010_actual" : "376",
  "fy_2012_actual" : "376",
  "fy_2014_actual" : "450",
  "fy_2015_actual" : "477",
  "fy_2016_actual" : "559"
}
, {
  "fy_2006_actual" : "-453519",
  "fy_2007_actual" : "-514796",
  "agency_name" : "Prior Payable Adjustment",
  "fy_2008_actual" : "-398740",
  "fy_2021_plan" : "0",
  "fy_2004_actual" : "-329182",
  "fy_2005_actual" : "-225860",
  "fy_2020_plan" : "0",
  "agn" : "989",
  "fy_2017_plan" : "-500000",
  "fy_2019_plan" : "0",
  "fy_2018_plan" : "0",
  "fy_2011_actual" : "-383838",
  "fy_2002_actual" : "-413262",
  "fy_2003_actual" : "-177968",
  "fy_2009_actual" : "-452764",
  "fy_2013_actual" : "-173848",
  "fy_2010_actual" : "-854416",
  "fy_2012_actual" : "-215463",
  "fy_2014_actual" : "-820670",
  "fy_2015_actual" : "-624354",
  "fy_2016_actual" : "-328554"
}
, {
  "fy_2006_actual" : "0",
  "fy_2007_actual" : "0",
  "agency_name" : "General Reserve",
  "fy_2008_actual" : "0",
  "fy_2021_plan" : "1000000",
  "fy_2004_actual" : "0",
  "fy_2005_actual" : "0",
  "fy_2020_plan" : "1000000",
  "agn" : "991",
  "fy_2017_plan" : "20000",
  "fy_2019_plan" : "1000000",
  "fy_2018_plan" : "1200000",
  "fy_2011_actual" : "0",
  "fy_2002_actual" : "0",
  "fy_2003_actual" : "0",
  "fy_2009_actual" : "0",
  "fy_2013_actual" : "0",
  "fy_2010_actual" : "0",
  "fy_2012_actual" : "0",
  "fy_2014_actual" : "0",
  "fy_2015_actual" : "0",
  "fy_2016_actual" : "0"
}
, {
  "fy_2006_actual" : "0",
  "fy_2007_actual" : "0",
  "agency_name" : "Citywide Savings Initiatives",
  "fy_2008_actual" : "0",
  "fy_2021_plan" : "-98781",
  "fy_2004_actual" : "0",
  "fy_2005_actual" : "0",
  "fy_2020_plan" : "-73531",
  "agn" : "992",
  "fy_2017_plan" : "0",
  "fy_2019_plan" : "-46281",
  "fy_2018_plan" : "0",
  "fy_2011_actual" : "0",
  "fy_2002_actual" : "0",
  "fy_2003_actual" : "0",
  "fy_2009_actual" : "0",
  "fy_2013_actual" : "0",
  "fy_2010_actual" : "0",
  "fy_2012_actual" : "0",
  "fy_2014_actual" : "0",
  "fy_2015_actual" : "0",
  "fy_2016_actual" : "0"
}
, {
  "fy_2006_actual" : "0",
  "fy_2007_actual" : "0",
  "agency_name" : "Energy Adjustment",
  "fy_2008_actual" : "0",
  "fy_2021_plan" : "101321",
  "fy_2004_actual" : "0",
  "fy_2005_actual" : "0",
  "fy_2020_plan" : "57776",
  "agn" : "995",
  "fy_2017_plan" : "0",
  "fy_2019_plan" : "22099",
  "fy_2018_plan" : "0",
  "fy_2011_actual" : "0",
  "fy_2002_actual" : "0",
  "fy_2003_actual" : "0",
  "fy_2009_actual" : "0",
  "fy_2013_actual" : "0",
  "fy_2010_actual" : "0",
  "fy_2012_actual" : "0",
  "fy_2014_actual" : "0",
  "fy_2015_actual" : "0",
  "fy_2016_actual" : "0"
}
, {
  "fy_2006_actual" : "0",
  "fy_2007_actual" : "0",
  "agency_name" : "Lease Adjustment",
  "fy_2008_actual" : "0",
  "fy_2021_plan" : "107056",
  "fy_2004_actual" : "0",
  "fy_2005_actual" : "0",
  "fy_2020_plan" : "70311",
  "agn" : "996",
  "fy_2017_plan" : "0",
  "fy_2019_plan" : "34636",
  "fy_2018_plan" : "0",
  "fy_2011_actual" : "0",
  "fy_2002_actual" : "0",
  "fy_2003_actual" : "0",
  "fy_2009_actual" : "0",
  "fy_2013_actual" : "0",
  "fy_2010_actual" : "0",
  "fy_2012_actual" : "0",
  "fy_2014_actual" : "0",
  "fy_2015_actual" : "0",
  "fy_2016_actual" : "0"
}
, {
  "fy_2006_actual" : "0",
  "fy_2007_actual" : "0",
  "agency_name" : "OTPS Inflation Adjustment",
  "fy_2008_actual" : "0",
  "fy_2021_plan" : "166557",
  "fy_2004_actual" : "0",
  "fy_2005_actual" : "0",
  "fy_2020_plan" : "111038",
  "agn" : "998",
  "fy_2017_plan" : "0",
  "fy_2019_plan" : "55519",
  "fy_2018_plan" : "0",
  "fy_2011_actual" : "0",
  "fy_2002_actual" : "0",
  "fy_2003_actual" : "0",
  "fy_2009_actual" : "0",
  "fy_2013_actual" : "0",
  "fy_2010_actual" : "0",
  "fy_2012_actual" : "0",
  "fy_2014_actual" : "0",
  "fy_2015_actual" : "0",
  "fy_2016_actual" : "0"
}
, {
  "fy_2006_actual" : "372197",
  "fy_2007_actual" : "1955309",
  "agency_name" : "Prepayment and Defeasance Adjustment",
  "fy_2008_actual" : "1602961",
  "fy_2021_plan" : "0",
  "fy_2004_actual" : "705916",
  "fy_2005_actual" : "1805707",
  "fy_2020_plan" : "0",
  "fy_2017_plan" : "131620",
  "fy_2019_plan" : "0",
  "fy_2018_plan" : "-4169125",
  "fy_2011_actual" : "95890",
  "fy_2002_actual" : "-2263063",
  "fy_2003_actual" : "736774",
  "fy_2009_actual" : "-2496716",
  "fy_2013_actual" : "571683",
  "fy_2010_actual" : "-1892941",
  "fy_2012_actual" : "-1279934",
  "fy_2014_actual" : "-839293",
  "fy_2015_actual" : "1496355",
  "fy_2016_actual" : "410767"
}
, {
  "fy_2006_actual" : "38370483",
  "fy_2007_actual" : "42697117",
  "agency_name" : "CITYWIDE TOTAL - CITY FUNDS",
  "fy_2008_actual" : "43931950",
  "fy_2021_plan" : "71857779",
  "fy_2004_actual" : "32575676",
  "fy_2005_actual" : "36947700",
  "fy_2020_plan" : "70000650",
  "fy_2017_plan" : "60297486",
  "fy_2019_plan" : "67874932",
  "fy_2018_plan" : "61458011",
  "fy_2011_actual" : "44659685",
  "fy_2002_actual" : "26567991",
  "fy_2003_actual" : "29935781",
  "fy_2009_actual" : "40960287",
  "fy_2013_actual" : "50315020",
  "fy_2010_actual" : "41868262",
  "fy_2012_actual" : "47544093",
  "fy_2014_actual" : "53974462",
  "fy_2015_actual" : "58042995",
  "fy_2016_actual" : "58724969"
}
 ]